Workbook

Sheet Summary
A1: Station House Express - store financials at a glance
A2: BBQ + Cubans counter: lunch 11-2:30, catering pickups until 7 pm, 1,500 sq ft, 32 seats, 5 days/week, meats from the commissary at cost + 25%. Prepared Oct 27, 2026.
B4: Conservative | C4: Base | D4: Strong
A5: Sales
A6: Sales per day | B6: ='Sales & P&L'!G25 -> 2339.675 | C6: ='Sales & P&L'!H25 -> 3599.5 | D6: ='Sales & P&L'!I25 -> 5039.3
A7: Sales per week | B7: ='Sales & P&L'!G27 -> 11698.375 | C7: ='Sales & P&L'!H27 -> 17997.5 | D7: ='Sales & P&L'!I27 -> 25196.5
A8: Sales per month | B8: ='Sales & P&L'!G36 -> 50653.964 | C8: ='Sales & P&L'!H36 -> 77929.175 | D8: ='Sales & P&L'!I36 -> 109100.85
A9: of which evening catering pickups | B9: ='Sales & P&L'!G35 -> 10683.842 | C9: ='Sales & P&L'!H35 -> 16436.68 | D9: ='Sales & P&L'!I35 -> 23011.352
A10: Costs (% of sales)
A11: Cost of goods (meat at transfer price + food + packaging) | B11: ='Sales & P&L'!G41/'Sales & P&L'!G36 -> 0.34471446 | C11: ='Sales & P&L'!H41/'Sales & P&L'!H36 -> 0.34471446 | D11: ='Sales & P&L'!I41/'Sales & P&L'!I36 -> 0.34471446
A12: Labor | B12: ='Sales & P&L'!G48/'Sales & P&L'!G36 -> 0.31831389 | C12: ='Sales & P&L'!H48/'Sales & P&L'!H36 -> 0.20690403 | D12: ='Sales & P&L'!I48/'Sales & P&L'!I36 -> 0.14778859
A13: Prime cost (COGS + labor) - target under 60% | B13: ='Sales & P&L'!G50 -> 0.66302834 | C13: ='Sales & P&L'!H50 -> 0.55161848 | D13: ='Sales & P&L'!I50 -> 0.49250305
A14: Occupancy | B14: ='Sales & P&L'!G54/'Sales & P&L'!G36 -> 0.18359866 | C14: ='Sales & P&L'!H54/'Sales & P&L'!H36 -> 0.11933913 | D14: ='Sales & P&L'!I54/'Sales & P&L'!I36 -> 0.085242236
A15: Profit
A16: Store EBITDA per month | B16: ='Sales & P&L'!G68 -> 1762.156 | C16: ='Sales & P&L'!H68 -> 18298.722 | D16: ='Sales & P&L'!I68 -> 37197.655
A17: Store EBITDA margin | B17: ='Sales & P&L'!G69 -> 0.034788116 | C17: ='Sales & P&L'!H69 -> 0.23481222 | D17: ='Sales & P&L'!I69 -> 0.34094745
A18: Commissary profit from this store per month (meat markup) | B18: ='Sales & P&L'!G72 -> 2018.173 | C18: ='Sales & P&L'!H72 -> 3104.8815 | D18: ='Sales & P&L'!I72 -> 4346.8341
A19: Combined Station House profit per month | B19: ='Sales & P&L'!G73 -> 3780.329 | C19: ='Sales & P&L'!H73 -> 21403.604 | D19: ='Sales & P&L'!I73 -> 41544.489
A20: Payback on startup cost (months) | B20: ='Sales & P&L'!G74 -> 264.57017 | C20: ='Sales & P&L'!H74 -> 25.477949 | D20: ='Sales & P&L'!I74 -> 12.533422
A21: Who makes money (per year)
A22: Investor share of store profit | B22: ='Who Makes Money'!B13 -> 2037.3115 | C22: ='Who Makes Money'!C13 -> 134071.12 | D22: ='Who Makes Money'!D13 -> 284966.89
A23: Investor cash-on-cash return | B23: ='Who Makes Money'!B14 -> 0.004369907 | C23: ='Who Makes Money'!C14 -> 0.28757425 | D23: ='Who Makes Money'!D14 -> 0.61123635
A24: Station House total (fee + ownership share + commissary markup) | B24: ='Who Makes Money'!B21 -> 43326.636 | C24: ='Who Makes Money'!C21 -> 122772.13 | D24: ='Who Makes Money'!D21 -> 213566.98
A25: One-number answers
A26: Startup cost - raw shell, 1st generation | C26: ='Startup Budget'!$F$47 -> 725305.71
A27: Startup cost - former restaurant, 2nd generation | C27: ='Startup Budget'!$G$47 -> 466213.91
A28: Startup cost used in this plan | C28: ='Startup Budget'!$F$50 -> 466213.91
A29: Break-even sales per day | C29: ='Break-Even'!$B$19 -> 2205.4266
A30: Break-even sales per week | C30: ='Break-Even'!$B$18 -> 11027.133
A31: Break-even tickets per day | C31: ='Break-Even'!$B$20 -> 47.124499
A32: Break-even per day incl. 20%/yr investor return | C32: ='Break-Even'!$B$28 -> 2797.3954
A33: Food + packaging cost: 5-Alarm Sampler 2-3 | C33: ='Menu Costing'!E43/'Menu Costing'!E44 -> 0.31957481
A34: Food + packaging cost: 5-Alarm Sampler 5-6 | C34: ='Menu Costing'!F43/'Menu Costing'!F44 -> 0.35865499
A35: Food + packaging cost: Brisket Cuban | C35: ='Menu Costing'!G43/'Menu Costing'!G44 -> 0.31725231
A36: Food + packaging cost: Smokin' Cuban | C36: ='Menu Costing'!H43/'Menu Costing'!H44 -> 0.25149474
A37: Food + packaging cost: fountain drink | C37: ='Menu Costing'!S43/'Menu Costing'!S44 -> 0.17531773
A38: Food + packaging cost: cornbread + tallow butter | C38: ='Menu Costing'!T43/'Menu Costing'!T44 -> 0.27375091
A39: Food + packaging cost: Party Sampler Feeds 20 | C39: ='Menu Costing'!V43/'Menu Costing'!V44 -> 0.42023966
A40: Annual meat savings going direct, base case (store only) | C40: ='Direct vs Distributor'!$I$11 -> 18929.172
A41: Annual meat savings going direct, base case (whole business) | C41: ='Direct vs Distributor'!$I$15 -> 56787.515
A42: Brisket: what you pay vs USDA wholesale | C42: ='Direct vs Distributor'!$E$5 -> 0.16260163
A44: Read me first: meat, sides, bread, deli, drinks and packaging are priced from the Station House order guide (Centerpoint, Cheney, US Foods, La Segunda). Still estimates: salami, a few spices, bananas/onions/peppers, the 25% commissary markup basis (smoke cost per lb), labor, NNN and build-out. Change any blue cell and every tab updates.
A45: Volumes are anchored to Seminole Heights Square data (Sep 18 - Oct 27, 2026). Rent ($6K) and the 25% commissary markup are Anthony's numbers. Everything else marked "Estimate" should be confirmed before it goes to an investor.

Sheet Assumptions
A1: Assumptions - every input in one place
A2: Blue = input you can change. Yellow = key assumption to confirm. Black = formula. Green = link to another tab.
A4: Operating calendar
A5: Days open per week (lunch only) | B5: 5 | C5: days | D5: From Anthony: 5-day week, lunch only (2 days off).
A6: Weeks per month | B6: 4.33 | C6: weeks | D6: 52 weeks / 12 months.
A7: Scenario volume: Conservative (x base) | B7: 0.65 | D7: Slow ramp / first 90 days.
A8: Scenario volume: Base (x base) | B8: 1 | D8: Base day = ~$2,800 sales (see Sales & P&L daily units).
A9: Scenario volume: Strong (x base) | B9: 1.4 | D9: Comparable to a strong Seminole Heights Saturday (~$2.9K) every day.
A10: Average ticket (Seminole Heights actual) | B10: 46.8 | C10: $ | D10: Square, Seminole Heights, Sep 18 - Oct 27, 2026: 1,000 completed orders, $46,804.
A11: Commissary (meats only)
A12: Commissary markup on meats (cost + %) | B12: 0.25 | D12: From Anthony: cost + 25%. Restaurant buys all other food and supplies itself.
A13: Commissary labor for this store (hours per week) | B13: 20 | C13: hrs/wk | D13: From Anthony: about 20 hours a week.
A14: Commissary pitmaster / prep hourly rate | B14: 18 | C14: $/hr | D14: Estimate - set to what you pay at the commissary.
A15: Wood cost per smoke (one smoker load) | B15: 15 | C15: $ | D15: From Anthony: ~$15 a smoke.
A16: Smokes per smoke day (2 smokers x 2 a day) | B16: 4 | D16: From Anthony: two smokers, twice a day.
A17: Smoke days per week for this store | B17: 3 | C17: days | D17: Sun / Mon / Tue cadence. Change if the store volume needs more or fewer.
A18: Vac bags, foil, labels per raw lb processed | B18: 0.08 | C18: $/lb | D18: Estimate.
A19: Deliveries per week (1 scheduled + emergencies) | B19: 1.5 | C19: runs | D19: From Anthony: one delivery a week plus an emergency run when needed (assumed every other week).
A20: Cost per delivery run (driver time + fuel + vehicle) | B20: 60 | C20: $/run | D20: Estimate: ~2 hrs driver + fuel/wear.
A21: Warehouse / commissary rent (monthly) | B21: 10100 | C21: $/mo | D21: From Anthony: $10,100/month.
A22: Share of warehouse rent charged to this store | B22: 0 | D22: Input. 0% = the store is extra volume through a commissary you already pay for (catering covers the rent). Try 10-20% to see a fully loaded view.
A23: Commissary process cost per raw lb (calculated on Commissary P&L) | B23: ='Commissary P&L'!$B$20 -> 1.2120984 | C23: $/lb | D23: Labor + wood + bags + delivery divided by raw pounds processed for this store. Feeds the transfer price.
A24: USDA wholesale benchmarks (what packers sell at, full truckloads)
A25: Brisket, whole packer IMPS 120, Prime | B25: 4.92 | C25: $/lb | D25: USDA AMS LM_XB456 weekly Prime, Oct 19 2026, avg $492/cwt (range $458-$634). Choice was $3.87 (LM_XB403, Oct 26).
A26: Pork butt, 1/4 trim | B26: 1.23 | C26: $/lb | D26: USDA pork cutout morning report Oct 13 2026 via IndexBox write-up (USDA report itself not reached).
A27: Spare ribs, trimmed medium | B27: 1.69 | C27: $/lb | D27: Same USDA pork report, Oct 13 2026.
A28: Pork belly, skin-on 10-12 lb | B28: 2.38 | C28: $/lb | D28: Same USDA pork report. Skinless 13-17 lb was $1.16 but skin-on is closer to what burnt ends use.
A29: Chicken leg quarters, bulk | B29: 0.529 | C29: $/lb | D29: USDA weekly chicken report, Oct 23 2026, avg $52.9/cwt.
A30: Meat prices you pay today (Station House order guide)
A31: Brisket, Prime whole packer | B31: 5.72 | C31: $/lb | D31: US Foods Prime, $5.72/lb (Anthony, Oct 27). Order guide still lists Centerpoint at $7.82/lb.
A32: Pork butt, cs 4x14# | B32: 2.07 | C32: $/lb | D32: Centerpoint, $115.92/cs.
A33: Spare ribs 5#+, cs 8/5#+ | B33: 2.89 | C33: $/lb | D33: Cheney, $115.60/cs.
A34: Pork belly skin-off | B34: 4.21 | C34: $/lb | D34: US Foods, $4.21/lb (Anthony, Oct 27).
A35: Chicken leg quarters, cs 4x10# | B35: 0.81 | C35: $/lb | D35: Centerpoint, $32.40/cs.
A36: Jalapeno cheddar sausage, cs 10# | B36: 5.89 | C36: $/lb | D36: Centerpoint, $58.90/cs.
A37: Expected savings buying direct vs today (base case) | B37: 0.15 | D37: Estimate. Sensitivity at 10% / 20% / 30% on Direct vs Distributor. Get a written packer or purveyor quote to replace this.
A38: Yields and portions
A39: Brisket cook + trim yield (raw packer to sliced) | B39: 0.5 | D39: Confirmed by Anthony: 50%.
A40: Pork butt yield (raw to pulled) | B40: 0.55 | D40: Rule of thumb 50-60%.
A41: Pork belly yield (raw to burnt ends) | B41: 0.6 | D41: Rule of thumb.
A42: Spare rib rack raw weight | B42: 3.5 | C42: lb | D42: Trimmed spare rack, typical 3-4 lb.
A43: Bones per rack | B43: 12 | C43: bones | D43: Typical spare rack 11-13 bones.
A44: Chicken leg quarter raw weight | B44: 0.75 | C44: lb | D44: Typical 10-14 oz.
A45: Sausage links per lb | B45: 4 | C45: links | D45: 4 oz links.
A46: Average raw packer brisket weight | B46: 14 | C46: lb | D46: For converting lbs to whole briskets.
A47: Average raw pork butt weight | B47: 9 | C47: lb
A48: Prep buffer over forecast | B48: 0.1 | D48: Extra prepped to avoid selling out; leftovers roll to next day (vac-sealed).
A49: Menu prices (pre-tax)
A50: 5-Alarm Sampler (2-3 people) | B50: 59.99 | D50: Current Walk-In Sampler 2-3 price in Square, renamed.
A51: 5-Alarm Sampler (5-6 people) | B51: 119.99 | D51: Current Walk-In Sampler 5-6 price in Square, renamed.
A52: Brisket Cuban | B52: 17.99 | D52: Current Square price.
A53: Smokin' Cuban | B53: 14.99 | D53: Raised $2 from $12.99 (Anthony, Oct 27). Brisket Cuban stays $17.99.
A54: Pre-order: Slow-Smoked Brisket (per lb) | B54: 45.99 | D54: Commerce / Square catering price.
A55: Pre-order: Pulled Pork (per lb) | B55: 18.99 | D55: Commerce price.
A56: Pre-order: Spare Ribs (per rack) | B56: 46.99 | D56: Commerce price.
A57: Pre-order: Pork Belly Burnt Ends (per lb) | B57: 36.99 | D57: Commerce price.
A58: Pre-order: Jalapeno Cheddar Sausage (per link) | B58: 5.99 | D58: Commerce price.
A59: Pre-order: Chicken Leg Quarter (each) | B59: 7.99 | D59: Commerce price.
A60: Side, 6 oz (mac, beans or slaw) | B60: 5.99 | D60: Commerce price.
A61: Banana Pudding (cup) | B61: 5.99 | D61: Seminole Heights Square price.
... A67: Party Sampler - Feeds 50 (catering) | B67: 1350 | D67: Commerce / Square catering price.
A68: Labor
A69: General manager salary (annual) | B69: 60000 | C69: $/yr | D69: Estimate. If Anthony runs the store himself, set to his draw or 0.
A70: Hourly crew on shift | B70: 3 | C70: people | D70: Cutter, Cubans/sides, pickup/to-go. GM works the register.
A71: Hours per crew member per day | B71: 7 | C71: hrs | D71: 8:30am prep to 3:30pm close-out.
A72: Crew hourly rate | B72: 16 | C72: $/hr | D72: Estimate for Tampa back-of-house.
A73: Payroll taxes + workers comp | B73: 0.11 | D73: FICA 7.65% + FUTA/SUTA + WC estimate.
A74: Evening catering pickup: crew on shift | B74: 1 | C74: people | D74: Catering pickups only after lunch, until 7:00 pm, so no extra line staff (Anthony, Oct 27).
A75: Evening catering pickup: hours per day (2:30-7:30) | B75: 5 | C75: hrs | D75: Stage orders, hand off, close at 7:00, clean down.
A76: Store smoker: extra crew hours per day (7:00 start for daily chicken) | B76: 1.5 | C76: hrs | D76: Estimate: opener comes in early to load the smoker; chicken ready by 10:30.
A77: Store smoker: smokes per day | B77: 1 | D77: Daily fresh chicken (Anthony: smoker at the store, daily smoke).
A78: Ownership - who makes money
A79: Station House (Anthony) ownership of the store | B79: 0.3 | D79: Input - deal not set. Operating partner share; investor owns the rest.
A80: Share of startup cost the investor puts in | B80: 1 | D80: Input. 100% = investor funds everything.
A81: Station House management / brand fee (% of store sales) | B81: 0.03 | D81: Input. Paid to Station House before profit split, for brand, systems, recipes and oversight. Set to 0% if not part of the deal.
A82: Space type the plan uses: 1 = raw shell (1st gen), 2 = former restaurant (2nd gen) | B82: 2 | D82: Drives payback and investor return. Both budgets are on Startup Budget.
A83: Occupancy and fixed costs (monthly)
A84: Base rent (1,500 sq ft) | B84: 6000 | C84: $/mo | D84: From Anthony: ~$6K/month.
A85: NNN / CAM (taxes, insurance, common area) | B85: 1500 | C85: $/mo | D85: Estimate ~$12/sf/yr. Confirm with landlord.
A86: Utilities (3-phase electric, water, gas) | B86: 1800 | C86: $/mo | D86: Estimate; combi + kettle + holding are electric.
A87: Insurance (GL, property, liquor n/a) | B87: 650 | C87: $/mo | D87: Estimate.
A88: Square software, KDS, online ordering | B88: 150 | C88: $/mo | D88: Estimate.
A89: Internet + phone (Quo) | B89: 200 | C89: $/mo | D89: Estimate.
A90: Towels / linens | B90: 650 | C90: $/mo | D90: Cintas renegotiated to ~$150/week.
A91: Pest control | B91: 100 | C91: $/mo | D91: Estimate.
A92: Trash + grease trap service | B92: 350 | C92: $/mo | D92: Estimate.
A93: Repairs + maintenance | B93: 500 | C93: $/mo | D93: Estimate.
A94: Bookkeeping / accounting | B94: 500 | C94: $/mo | D94: Estimate.
A95: Licenses + permits (monthly allowance) | B95: 100 | C95: $/mo | D95: DBPR, city/county BTR, fire inspection.
A96: Variable costs (% of sales)
A97: Card processing (Square) | B97: 0.029 | D97: Square in-person 2.6% + $0.15 on a ~$47 ticket = ~2.9%.
A98: Marketing | B98: 0.02 | D98: Estimate.
A99: Waste / comps (% of food cost) | B99: 0.03 | D99: Estimate.

Sheet Meat Cost & Transfer
A1: Meat cost and commissary transfer price
A2: Commissary buys raw meat, smokes, chills and vac-packs it, then sells it to the store at cost + markup. Store pays the transfer price.
A4: Protein | B4: Unit sold to store | C4: USDA $/lb | D4: You pay today $/lb (order guide) | E4: Raw lb per unit | F4: Raw cost per unit | G4: Commissary process cost per unit (labor, wood, bags, delivery) | H4: Commissary cost per unit | I4: Markup | J4: Store pays (transfer) | K4: Commissary profit per unit
A5: Brisket (sliced) | B5: cooked lb | C5: =Assumptions!$B$25 -> 4.92 | D5: =Assumptions!$B$31 -> 5.72 | E5: =1/Assumptions!$B$39 -> 2 | F5: =D5*E5 -> 11.44 | G5: =E5*Assumptions!$B$23 -> 2.4241967 | H5: =F5+G5 -> 13.864197 | I5: =Assumptions!$B$12 -> 0.25 | J5: =H5*(1+I5) -> 17.330246 | K5: =J5-H5 -> 3.4660492
A6: Pulled pork | B6: cooked lb | C6: =Assumptions!$B$26 -> 1.23 | D6: =Assumptions!$B$32 -> 2.07 | E6: =1/Assumptions!$B$40 -> 1.8181818 | F6: =D6*E6 -> 3.7636364 | G6: =E6*Assumptions!$B$23 -> 2.2038152 | H6: =F6+G6 -> 5.9674516 | I6: =Assumptions!$B$12 -> 0.25 | J6: =H6*(1+I6) -> 7.4593145 | K6: =J6-H6 -> 1.4918629
A7: Pork belly burnt ends | B7: cooked lb | C7: =Assumptions!$B$28 -> 2.38 | D7: =Assumptions!$B$34 -> 4.21 | E7: =1/Assumptions!$B$41 -> 1.6666667 | F7: =D7*E7 -> 7.0166667 | G7: =E7*Assumptions!$B$23 -> 2.0201639 | H7: =F7+G7 -> 9.0368306 | I7: =Assumptions!$B$12 -> 0.25 | J7: =H7*(1+I7) -> 11.296038 | K7: =J7-H7 -> 2.2592077
A8: Spare ribs | B8: rack | C8: =Assumptions!$B$27 -> 1.69 | D8: =Assumptions!$B$33 -> 2.89 | E8: =Assumptions!$B$42 -> 3.5 | F8: =D8*E8 -> 10.115 | G8: =E8*Assumptions!$B$23 -> 4.2423443 | H8: =F8+G8 -> 14.357344 | I8: =Assumptions!$B$12 -> 0.25 | J8: =H8*(1+I8) -> 17.94668 | K8: =J8-H8 -> 3.5893361
A9: Chicken leg quarter | B9: each | C9: =Assumptions!$B$29 -> 0.529 | D9: =Assumptions!$B$35 -> 0.81 | E9: =Assumptions!$B$44 -> 0.75 | F9: =D9*E9 -> 0.6075 | G9: 0 | H9: =F9+G9 -> 0.6075 | I9: =Assumptions!$B$12 -> 0.25 | J9: =H9*(1+I9) -> 0.759375 | K9: =J9-H9 -> 0.151875 | L9: Raw on the weekly delivery; smoked fresh daily at the store
A10: Jalapeno cheddar sausage | B10: link | C10: n/a | D10: =Assumptions!$B$36 -> 5.89 | E10: =1/Assumptions!$B$45 -> 0.25 | F10: =D10*E10 -> 1.4725 | G10: =E10*Assumptions!$B$23 -> 0.30302459 | H10: =F10+G10 -> 1.7755246 | I10: =Assumptions!$B$12 -> 0.25 | J10: =H10*(1+I10) -> 2.2194057 | K10: =J10-H10 -> 0.44388115
A12: Rib bone (for samplers) | B12: bone | H12: =H8/Assumptions!$B$43 -> 1.1964454 | J12: =J8/Assumptions!$B$43 -> 1.4955567 | K12: =J12-H12 -> 0.29911134
A14: How to read this: "Store pays" is what the restaurant is charged per unit and is what Menu Costing uses. Purchase prices are what you pay today per the Station House order guide (Centerpoint / Cheney). USDA is shown only as a benchmark; see Direct vs Distributor.
A15: Brisket price warning: in late Sept 2026 USDA grocery brisket specials jumped from $5.29 to $11.05/lb and some BBQ operators saw wholesale go from <$6 to ~$8/lb (KY3, Sep 29 2026). Re-check before you sign anything.

Sheet Sides & Ingredients
A1: Sides, desserts, bread, sauces and packaging - store buys these
A2: Prices from the Station House order guide (Cheney, US Foods, La Segunda) where listed; column G says which. Lines marked Estimate are not in the order guide.
A4: House BBQ sauce (Sweet Eddie / Carolina Gold / Spicy avg) (batch yields 128 oz)
A5: Ingredient | B5: Qty / batch | C5: Unit | D5: Cost per unit | E5: Batch cost | F5: Buy as (pack) | G5: Note
A6: Ketchup, #10 can | B6: 1 | C6: can | D6: 7.8533 | E6: =B6*D6 -> 7.8533 | F6: 6 x #10 case | G6: Order guide: Cheney 6/#10 $47.12
A7: Brown sugar | B7: 2 | C7: lb | D7: 1.3372 | E7: =B7*D7 -> 2.6744 | F7: 25 lb bag | G7: Order guide: Cheney 25# $33.43
A8: Vinegar | B8: 16 | C8: oz | D8: 0.0403 | E8: =B8*D8 -> 0.6448 | F8: 4 x 1 gal | G8: Order guide: Cheney distilled 4/1gal $20.61
A9: Worcestershire | B9: 8 | C9: oz | D9: 0.12 | E9: =B9*D9 -> 0.96 | F9: 4 x 1 gal | G9: Estimate
A10: Spices / rub | B10: 1 | C10: batch | D10: 2 | E10: =B10*D10 -> 2 | F10: Flashover rub, in-house | G10: Estimate
A11: Batch cost | E11: =SUM(E6:E10) -> 14.1325
A12: Batch yield (oz) | E12: 128
A13: Cost per oz | E13: =E11/E12 -> 0.11041016
A15: Beef tallow smoked mac & cheese (batch yields 256 oz)
A16: Ingredient | B16: Qty / batch | C16: Unit | D16: Cost per unit | E16: Batch cost | F16: Buy as (pack) | G16: Note
A17: Cavatappi | B17: 4 | C17: lb | D17: 1.796 | E17: =B17*D17 -> 7.184 | F17: 4 x 5 lb | G17: Order guide: US Foods 4/5# $35.92
A18: Smoked cheddar | B18: 3 | C18: lb | D18: 5.59 | E18: =B18*D18 -> 16.77 | F18: 4 x 2.25 lb | G18: Order guide: Cheney 4/2.25# $50.31
A19: Smoked gouda | B19: 3 | C19: lb | D19: 5.27 | E19: =B19*D19 -> 15.81 | F19: 2 x 6 lb | G19: Order guide: US Foods $5.27 (listed; confirm $/lb)
A20: Whole milk | B20: 1 | C20: gal | D20: 6.6025 | E20: =B20*D20 -> 6.6025 | F20: 4 x 1 gal | G20: Order guide: Cheney 4/1gal $26.41
A21: Heavy cream | B21: 2 | C21: qt | D21: 4.6308 | E21: =B21*D21 -> 9.2616 | F21: 12 x 1 qt | G21: Order guide: Cheney 12/1qt $55.57
A22: Butter | B22: 1 | C22: lb | D22: 2.3339 | E22: =B22*D22 -> 2.3339 | F22: 36 x 1 lb | G22: Order guide: US Foods 36/1# $84.02
A23: Seasoning | B23: 1 | C23: batch | D23: 1.5 | E23: =B23*D23 -> 1.5 | G23: Estimate
A24: Batch cost | E24: =SUM(E17:E23) -> 59.462
A25: Batch yield (oz) | E25: 256
A26: Cost per oz | E26: =E24/E25 -> 0.23227344
A28: Cowboy beans (brisket) (batch yields 340 oz)
A29: Ingredient | B29: Qty / batch | C29: Unit | D29: Cost per unit | E29: Batch cost | F29: Buy as (pack) | G29: Note
A30: Baked beans, #10 can | B30: 3 | C30: can | D30: 7.6883 | E30: =B30*D30 -> 23.0649 | F30: 6 x #10 case | G30: Order guide: US Foods 6/#10 $46.13
A31: Brisket trim / burnt ends trim | B31: 2 | C31: lb | D31: 2 | E31: =B31*D31 -> 4 | F31: commissary trim (internal value) | G31: Estimate
A32: Yellow onion | B32: 1 | C32: lb | D32: 0.9 | E32: =B32*D32 -> 0.9 | F32: 50 lb sack | G32: Estimate
A33: Bell pepper | B33: 0.5 | C33: lb | D33: 1.5 | E33: =B33*D33 -> 0.75 | F33: case | G33: Estimate
A34: House BBQ sauce | B34: 32 | C34: oz | D34: ='Sides & Ingredients'!$E$13 -> 0.11041016 | E34: =B34*D34 -> 3.533125
A35: Brown sugar | B35: 1 | C35: lb | D35: 1.3372 | E35: =B35*D35 -> 1.3372 | F35: 25 lb bag | G35: Order guide: Cheney 25# $33.43
A36: Mustard / spice | B36: 1 | C36: batch | D36: 1 | E36: =B36*D36 -> 1 | G36: Estimate
A37: Batch cost | E37: =SUM(E30:E36) -> 34.585225
A38: Batch yield (oz) | E38: 340
A39: Cost per oz | E39: =E37/E38 -> 0.10172125
A41: Apple coleslaw (batch yields 160 oz)
A42: Ingredient | B42: Qty / batch | C42: Unit | D42: Cost per unit | E42: Batch cost | F42: Buy as (pack) | G42: Note
A43: Coleslaw mix | B43: 5 | C43: lb | D43: 1.5155 | E43: =B43*D43 -> 7.5775 | F43: 4 x 5 lb | G43: Order guide: Cheney 4/5# $30.31
A44: Apples | B44: 3 | C44: lb | D44: 1.4136 | E44: =B44*D44 -> 4.2408 | F44: 12 x 3 lb | G44: Order guide: Cheney 12/3# $50.89
A45: Mayonnaise | B45: 64 | C45: oz | D45: 0.1104 | E45: =B45*D45 -> 7.0656 | F45: 4 x 1 gal | G45: Order guide: US Foods 4/1gal $56.53
A46: Vinegar | B46: 16 | C46: oz | D46: 0.05 | E46: =B46*D46 -> 0.8 | F46: 4 x 1 gal | G46: Estimate
A47: Sugar | B47: 1 | C47: lb | D47: 0.7832 | E47: =B47*D47 -> 0.7832 | F47: 50 lb bag | G47: Order guide: Cheney 50# $39.16
A48: Seasoning | B48: 1 | C48: batch | D48: 0.5 | E48: =B48*D48 -> 0.5 | G48: Estimate
A49: Batch cost | E49: =SUM(E43:E48) -> 20.9671
A50: Batch yield (oz) | E50: 160
A51: Cost per oz | E51: =E49/E50 -> 0.13104437
A53: From-scratch banana pudding (batch yields 24 cups)
A54: Ingredient | B54: Qty / batch | C54: Unit | D54: Cost per unit | E54: Batch cost | F54: Buy as (pack) | G54: Note
A55: Vanilla pudding base | B55: 2 | C55: lb | D55: 4.5 | E55: =B55*D55 -> 9 | F55: 6 x #10 or 12 x 2 lb | G55: Estimate
A56: Whole milk | B56: 1 | C56: gal | D56: 6.6025 | E56: =B56*D56 -> 6.6025 | F56: 4 x 1 gal | G56: Order guide: Cheney 4/1gal $26.41
A57: Bananas | B57: 6 | C57: lb | D57: 0.65 | E57: =B57*D57 -> 3.9 | F57: 40 lb case | G57: Estimate
A58: Vanilla wafers | B58: 2 | C58: lb | D58: 5.39 | E58: =B58*D58 -> 10.78 | F58: 2 x 2 lb | G58: Order guide: Cheney 2/2# $21.56
A59: Whipped topping | B59: 2 | C59: lb | D59: 3.5 | E59: =B59*D59 -> 7 | F59: case | G59: Estimate
A60: Batch cost | E60: =SUM(E55:E59) -> 37.2825
A61: Batch yield (cups) | E61: 24
A62: Cost per cup | E62: =E60/E61 -> 1.5534375
A64: Pickled red onions (batch yields 80 oz)
A65: Ingredient | B65: Qty / batch | C65: Unit | D65: Cost per unit | E65: Batch cost | F65: Buy as (pack) | G65: Note
A66: Red onions | B66: 5 | C66: lb | D66: 1.0388 | E66: =B66*D66 -> 5.194 | F66: 25 lb | G66: Order guide: Cheney 25# $25.97
A67: Vinegar | B67: 32 | C67: oz | D67: 0.0403 | E67: =B67*D67 -> 1.2896 | F67: 4 x 1 gal | G67: Order guide: Cheney 4/1gal $20.61
A68: Sugar | B68: 0.5 | C68: lb | D68: 0.7832 | E68: =B68*D68 -> 0.3916 | F68: 50 lb bag | G68: Order guide: Cheney 50# $39.16
A69: Salt / spice | B69: 1 | C69: batch | D69: 0.3 | E69: =B69*D69 -> 0.3 | G69: Estimate
A70: Batch cost | E70: =SUM(E66:E69) -> 7.1752
A71: Batch yield (oz) | E71: 80
A72: Cost per oz | E72: =E70/E71 -> 0.08969
A74: Jerk mayo-mustard-relish aioli (Smokin' Cuban) (batch yields 64 oz)
A75: Ingredient | B75: Qty / batch | C75: Unit | D75: Cost per unit | E75: Batch cost | F75: Buy as (pack) | G75: Note
A76: Mayonnaise | B76: 48 | C76: oz | D76: 0.1104 | E76: =B76*D76 -> 5.2992 | F76: 4 x 1 gal | G76: Order guide: US Foods 4/1gal $56.53
A77: Yellow mustard | B77: 8 | C77: oz | D77: 0.0784 | E77: =B77*D77 -> 0.6272 | F77: 4 x 1 gal | G77: Order guide: Cheney 4/1gal $40.14
A78: Sweet relish | B78: 8 | C78: oz | D78: 0.1 | E78: =B78*D78 -> 0.8 | F78: 4 x 1 gal | G78: Estimate
A79: Jerk seasoning | B79: 1 | C79: batch | D79: 1 | E79: =B79*D79 -> 1 | G79: Estimate
A80: Batch cost | E80: =SUM(E76:E79) -> 7.7264
A81: Batch yield (oz) | E81: 64
A82: Cost per oz | E82: =E80/E81 -> 0.120725
A84: Guava BBQ sauce (batch yields 96 oz)
A85: Ingredient | B85: Qty / batch | C85: Unit | D85: Cost per unit | E85: Batch cost | F85: Buy as (pack) | G85: Note
A86: Guava paste | B86: 2 | C86: lb | D86: 3.5 | E86: =B86*D86 -> 7 | F86: case | G86: Estimate
A87: House BBQ sauce | B87: 64 | C87: oz | D87: ='Sides & Ingredients'!$E$13 -> 0.11041016 | E87: =B87*D87 -> 7.06625
A88: Vinegar | B88: 8 | C88: oz | D88: 0.0403 | E88: =B88*D88 -> 0.3224 | F88: 4 x 1 gal | G88: Order guide: Cheney 4/1gal $20.61
A89: Batch cost | E89: =SUM(E86:E88) -> 14.38865
A90: Batch yield (oz) | E90: 96
A91: Cost per oz | E91: =E89/E90 -> 0.14988177
A93: Cornbread (sheet pan) (batch yields 40 pieces)
A94: Ingredient | B94: Qty / batch | C94: Unit | D94: Cost per unit | E94: Batch cost | F94: Buy as (pack) | G94: Note
A95: Cornbread mix, 64 oz bag | B95: 1 | C95: bag | D95: 14.73 | E95: =B95*D95 -> 14.73 | F95: 4 x 64 oz | G95: Order guide: US Foods 4/64oz $58.92
A96: Eggs | B96: 6 | C96: each | D96: 0.1483 | E96: =B96*D96 -> 0.8898 | F96: 15 dozen | G96: Order guide: US Foods 15 dz $26.70
A97: Whole milk | B97: 0.5 | C97: gal | D97: 6.6025 | E97: =B97*D97 -> 3.30125 | F97: 4 x 1 gal | G97: Order guide: Cheney 4/1gal $26.41
A98: Butter (melted, in batter) | B98: 0.5 | C98: lb | D98: 2.3339 | E98: =B98*D98 -> 1.16695 | F98: 36 x 1 lb | G98: Order guide: US Foods 36/1# $84.02
A99: Batch cost | E99: =SUM(E95:E98) -> 20.088
A100: Batch yield (pieces) | E100: 40
A101: Cost per piece | E101: =E99/E100 -> 0.5022
A103: Tallow honey butter (batch yields 32 oz)
A104: Ingredient | B104: Qty / batch | C104: Unit | D104: Cost per unit | E104: Batch cost | F104: Buy as (pack) | G104: Note
A105: Butter | B105: 1.25 | C105: lb | D105: 2.3339 | E105: =B105*D105 -> 2.917375 | F105: 36 x 1 lb | G105: Order guide: US Foods 36/1# $84.02
A106: Beef tallow (rendered brisket trim) | B106: 0.5 | C106: lb | D106: 1 | E106: =B106*D106 -> 0.5 | F106: commissary trim (internal value) | G106: Estimate
A107: Honey | B107: 4 | C107: oz | D107: 0.1462 | E107: =B107*D107 -> 0.5848 | F107: 6 x 5 lb | G107: Order guide: Cheney 6/5# $70.16
A108: Salt | B108: 1 | C108: batch | D108: 0.05 | E108: =B108*D108 -> 0.05 | G108: Estimate
A109: Batch cost | E109: =SUM(E105:E108) -> 4.052175
A110: Batch yield (oz) | E110: 32
...

Sheet Menu Costing
A1: Menu costing - plate cost of every item
A2: Each column is a menu item; each row is a component and how much of it the item uses. Plate cost = quantity x unit cost. Meats are costed at the commissary transfer price.
A4: Component | B4: Unit | C4: Category | D4: Unit cost | E4: 5-Alarm Sampler 2-3 | F4: 5-Alarm Sampler 5-6 | G4: Brisket Cuban | H4: Smokin' Cuban | I4: Pre-order Brisket /lb | J4: Pre-order Pulled Pork /lb | K4: Pre-order Spare Ribs /rack | L4: Pre-order Burnt Ends /lb | M4: Pre-order Sausage /link | N4: Pre-order Chicken LQ | O4: Mac & Cheese 6 oz | P4: Cowboy Beans 6 oz | Q4: Apple Slaw 6 oz | R4: Banana Pudding | S4: Fountain drink | T4: Cornbread + tallow butter | U4: Party Sampler Feeds 10 | V4: Party Sampler Feeds 20 | W4: Party Sampler Feeds 30 | X4: Party Sampler Feeds 50
A5: Brisket (sliced) | B5: cooked lb | C5: Meat | D5: ='Meat Cost & Transfer'!$J$5 -> 17.330246 | E5: 0.25 | F5: 0.5 | G5: 0.25 | I5: 1 | U5: 1 | V5: 2 | W5: 3 | X5: 5
A6: Pulled pork | B6: cooked lb | C6: Meat | D6: ='Meat Cost & Transfer'!$J$6 -> 7.4593145 | E6: 0.25 | F6: 0.5 | H6: 0.1875 | J6: 1 | U6: 2.5 | V6: 5 | W6: 7.5 | X6: 12.5
A7: Burnt ends | B7: cooked lb | C7: Meat | D7: ='Meat Cost & Transfer'!$J$7 -> 11.296038 | L7: 1
A8: Spare rib (bone) | B8: bone | C8: Meat | D8: ='Meat Cost & Transfer'!$J$12 -> 1.4955567 | E8: 2 | F8: 6 | K8: 12 | U8: 6 | V8: 12 | W8: 18 | X8: 24
A9: Chicken leg quarter | B9: each | C9: Meat | D9: ='Meat Cost & Transfer'!$J$9 -> 0.759375 | E9: 1 | F9: 2 | N9: 1 | U9: 3 | V9: 6 | W9: 9 | X9: 15
A10: Jalapeno cheddar sausage | B10: link | C10: Meat | D10: ='Meat Cost & Transfer'!$J$10 -> 2.2194057 | E10: 1 | F10: 2 | M10: 1 | U10: 4 | V10: 8 | W10: 12 | X10: 20
A11: Mac & cheese | B11: oz | C11: Food | D11: ='Sides & Ingredients'!$E$26 -> 0.23227344 | E11: 8 | F11: 32 | O11: 6 | U11: 128 | V11: 256 | W11: 256 | X11: 512
A12: Cowboy beans | B12: oz | C12: Food | D12: ='Sides & Ingredients'!$E$39 -> 0.10172125 | E12: 8 | F12: 16 | P12: 6 | U12: 32 | V12: 128 | W12: 128 | X12: 256
A13: Apple coleslaw | B13: oz | C13: Food | D13: ='Sides & Ingredients'!$E$51 -> 0.13104437 | Q13: 6 | U13: 32 | V13: 128 | W13: 128 | X13: 256
A14: Banana pudding | B14: cup | C14: Food | D14: ='Sides & Ingredients'!$E$62 -> 1.5534375 | R14: 1
A15: Texas toast | B15: slice | C15: Food | D15: ='Sides & Ingredients'!$D$115 -> 0.2793 | E15: 4 | F15: 6 | U15: 20 | V15: 40 | W15: 60 | X15: 100
A16: Pickles | B16: oz | C16: Food | D16: ='Sides & Ingredients'!$D$116 -> 0.1367 | E16: 1 | F16: 2 | U16: 8 | V16: 16 | W16: 32 | X16: 32
A17: Pickled onions | B17: oz | C17: Food | D17: ='Sides & Ingredients'!$E$72 -> 0.08969 | E17: 1 | F17: 2 | G17: 0.5 | U17: 8 | V17: 16 | W17: 16 | X17: 16
A18: BBQ sauce | B18: oz | C18: Food | D18: ='Sides & Ingredients'!$E$13 -> 0.11041016 | E18: 6 | F18: 6 | I18: 2 | J18: 2 | K18: 2 | U18: 16 | V18: 32 | W18: 64 | X18: 64
A19: Cuban bread | B19: each | C19: Food | D19: ='Sides & Ingredients'!$D$117 -> 0.47 | G19: 1 | H19: 1
A20: Swiss | B20: oz | C20: Food | D20: ='Sides & Ingredients'!$D$118 -> 0.2831 | G20: 1.5 | H20: 1.5
A21: Ham | B21: oz | C21: Food | D21: ='Sides & Ingredients'!$D$119 -> 0.2806 | H21: 2
A22: Salami | B22: oz | C22: Food | D22: ='Sides & Ingredients'!$D$120 -> 0.375 | H22: 1
A23: Jerk aioli | B23: oz | C23: Food | D23: ='Sides & Ingredients'!$E$82 -> 0.120725 | G23: 0.5 | H23: 0.75
A24: Guava BBQ | B24: oz | C24: Food | D24: ='Sides & Ingredients'!$E$91 -> 0.14988177 | H24: 0.5
A25: Butter | B25: oz | C25: Food | D25: ='Sides & Ingredients'!$D$121 -> 0.1459 | G25: 0.5 | H25: 0.5
A26: Fountain drink | B26: each | C26: Food | D26: ='Sides & Ingredients'!$D$128 -> 0.5242 | S26: 1
A27: Cornbread | B27: piece | C27: Food | D27: ='Sides & Ingredients'!$E$101 -> 0.5022 | T27: 1
A28: Tallow honey butter | B28: oz | C28: Food | D28: ='Sides & Ingredients'!$E$111 -> 0.12663047 | T28: 0.5
A29: Pack: sampler 2-3 | B29: each | C29: Packaging | D29: ='Sides & Ingredients'!$D$122 -> 2.326 | E29: 1
A30: Pack: sampler 5-6 | B30: each | C30: Packaging | D30: ='Sides & Ingredients'!$D$123 -> 3.858 | F30: 1
A31: Pack: Cuban | B31: each | C31: Packaging | D31: ='Sides & Ingredients'!$D$124 -> 0.302 | G31: 1 | H31: 1
A32: Pack: side cup | B32: each | C32: Packaging | D32: ='Sides & Ingredients'!$D$125 -> 0.253 | O32: 1 | P32: 1 | Q32: 1 | T32: 1
A33: Pack: pudding cup | B33: each | C33: Packaging | D33: ='Sides & Ingredients'!$D$126 -> 0.303 | R33: 1
A34: Pack: pre-order pan | B34: each | C34: Packaging | D34: ='Sides & Ingredients'!$D$127 -> 1.944 | I34: 1 | J34: 1 | K34: 1 | L34: 1
A35: Pack: Party Sampler 10 | B35: each | C35: Packaging | D35: ='Sides & Ingredients'!$D$129 -> 11.016 | U35: 1
A36: Pack: Party Sampler 20 | B36: each | C36: Packaging | D36: ='Sides & Ingredients'!$D$130 -> 19.738 | V36: 1
A37: Pack: Party Sampler 30 | B37: each | C37: Packaging | D37: ='Sides & Ingredients'!$D$131 -> 25.997 | W37: 1
A38: Pack: Party Sampler 50 | B38: each | C38: Packaging | D38: ='Sides & Ingredients'!$D$132 -> 42.347 | X38: 1
A40: Meat cost | E40: =SUMPRODUCT(($C$5:$C$38="Meat")*E$5:E$38*$D$5:$D$38) -> 12.167284 | F40: =SUMPRODUCT(($C$5:$C$38="Meat")*F$5:F$38*$D$5:$D$38) -> 27.325682 | G40: =SUMPRODUCT(($C$5:$C$38="Meat")*G$5:G$38*$D$5:$D$38) -> 4.3325615 | H40: =SUMPRODUCT(($C$5:$C$38="Meat")*H$5:H$38*$D$5:$D$38) -> 1.3986215 | I40: =SUMPRODUCT(($C$5:$C$38="Meat")*I$5:I$38*$D$5:$D$38) -> 17.330246 | J40: =SUMPRODUCT(($C$5:$C$38="Meat")*J$5:J$38*$D$5:$D$38) -> 7.4593145 | K40: =SUMPRODUCT(($C$5:$C$38="Meat")*K$5:K$38*$D$5:$D$38) -> 17.94668 | L40: =SUMPRODUCT(($C$5:$C$38="Meat")*L$5:L$38*$D$5:$D$38) -> 11.296038 | ... X40: =SUMPRODUCT(($C$5:$C$38="Meat")*X$5:X$38*$D$5:$D$38) -> 271.56476
A41: Other food cost | E41: =SUMPRODUCT(($C$5:$C$38="Food")*E$5:E$38*$D$5:$D$38) -> 4.6780084 | F41: =SUMPRODUCT(($C$5:$C$38="Food")*F$5:F$38*$D$5:$D$38) -> 11.851331 | G41: =SUMPRODUCT(($C$5:$C$38="Food")*G$5:G$38*$D$5:$D$38) -> 1.0728075 | H41: =SUMPRODUCT(($C$5:$C$38="Food")*H$5:H$38*$D$5:$D$38) -> 2.0692846 | I41: =SUMPRODUCT(($C$5:$C$38="Food")*I$5:I$38*$D$5:$D$38) -> 0.22082031 | J41: =SUMPRODUCT(($C$5:$C$38="Food")*J$5:J$38*$D$5:$D$38) -> 0.22082031 | K41: =SUMPRODUCT(($C$5:$C$38="Food")*K$5:K$38*$D$5:$D$38) -> 0.22082031 | L41: =SUMPRODUCT(($C$5:$C$38="Food")*L$5:L$38*$D$5:$D$38) -> 0 | ... X41: =SUMPRODUCT(($C$5:$C$38="Food")*X$5:X$38*$D$5:$D$38) -> 219.31769
A42: Packaging | E42: =SUMPRODUCT(($C$5:$C$38="Packaging")*E$5:E$38*$D$5:$D$38) -> 2.326 | F42: =SUMPRODUCT(($C$5:$C$38="Packaging")*F$5:F$38*$D$5:$D$38) -> 3.858 | G42: =SUMPRODUCT(($C$5:$C$38="Packaging")*G$5:G$38*$D$5:$D$38) -> 0.302 | H42: =SUMPRODUCT(($C$5:$C$38="Packaging")*H$5:H$38*$D$5:$D$38) -> 0.302 | I42: =SUMPRODUCT(($C$5:$C$38="Packaging")*I$5:I$38*$D$5:$D$38) -> 1.944 | J42: =SUMPRODUCT(($C$5:$C$38="Packaging")*J$5:J$38*$D$5:$D$38) -> 1.944 | K42: =SUMPRODUCT(($C$5:$C$38="Packaging")*K$5:K$38*$D$5:$D$38) -> 1.944 | L42: =SUMPRODUCT(($C$5:$C$38="Packaging")*L$5:L$38*$D$5:$D$38) -> 1.944 | ... X42: =SUMPRODUCT(($C$5:$C$38="Packaging")*X$5:X$38*$D$5:$D$38) -> 42.347
A43: Total plate cost | E43: =E40+E41+E42 -> 19.171293 | F43: =F40+F41+F42 -> 43.035013 | G43: =G40+G41+G42 -> 5.707369 | H43: =H40+H41+H42 -> 3.7699061 | I43: =I40+I41+I42 -> 19.495066 | J43: =J40+J41+J42 -> 9.6241348 | K43: =K40+K41+K42 -> 20.111501 | L43: =L40+L41+L42 -> 13.240038 | ... X43: =X40+X41+X42 -> 533.22945
A44: Menu price | E44: =Assumptions!$B$50 -> 59.99 | F44: =Assumptions!$B$51 -> 119.99 | G44: =Assumptions!$B$52 -> 17.99 | H44: =Assumptions!$B$53 -> 14.99 | I44: =Assumptions!$B$54 -> 45.99 | J44: =Assumptions!$B$55 -> 18.99 | K44: =Assumptions!$B$56 -> 46.99 | L44: =Assumptions!$B$57 -> 36.99 | M44: =Assumptions!$B$58 -> 5.99 | N44: =Assumptions!$B$59 -> 7.99 | O44: =Assumptions!$B$60 -> 5.99 | P44: =Assumptions!$B$60 -> 5.99 | Q44: =Assumptions!$B$60 -> 5.99 | R44: =Assumptions!$B$61 -> 5.99 | S44: =Assumptions!$B$62 -> 2.99 | T44: =Assumptions!$B$63 -> 2.99 | U44: =Assumptions!$B$64 -> 289 | V44: =Assumptions!$B$65 -> 570 | W44: =Assumptions!$B$66 -> 825 | X44: =Assumptions!$B$67 -> 1350
A45: Food + packaging cost % | E45: =IF(E44=0,0,E43/E44) -> 0.31957481 | F45: =IF(F44=0,0,F43/F44) -> 0.35865499 | G45: =IF(G44=0,0,G43/G44) -> 0.31725231 | H45: =IF(H44=0,0,H43/H44) -> 0.25149474 | I45: =IF(I44=0,0,I43/I44) -> 0.42389794 | J45: =IF(J44=0,0,J43/J44) -> 0.50680015 | K45: =IF(K44=0,0,K43/K44) -> 0.42799533 | L45: =IF(L44=0,0,L43/L44) -> 0.35793561 | ... X45: =IF(X44=0,0,X43/X44) -> 0.39498478
A46: Gross profit per item | E46: =E44-E43 -> 40.818707 | F46: =F44-F43 -> 76.954987 | G46: =G44-G43 -> 12.282631 | H46: =H44-H43 -> 11.220094 | I46: =I44-I43 -> 26.494934 | J46: =J44-J43 -> 9.3658652 | K46: =K44-K43 -> 26.878499 | L46: =L44-L43 -> 23.749962 | ... X46: =X44-X43 -> 816.77055
A47: Commissary profit inside this item (meat markup) | E47: =E40-E40/(1+Assumptions!$B$12) -> 2.4334568 | F47: =F40-F40/(1+Assumptions!$B$12) -> 5.4651364 | G47: =G40-G40/(1+Assumptions!$B$12) -> 0.8665123 | H47: =H40-H40/(1+Assumptions!$B$12) -> 0.27972429 | I47: =I40-I40/(1+Assumptions!$B$12) -> 3.4660492 | J47: =J40-J40/(1+Assumptions!$B$12) -> 1.4918629 | K47: =K40-K40/(1+Assumptions!$B$12) -> 3.5893361 | L47: =L40-L40/(1+Assumptions!$B$12) -> 2.2592077 | ... X47: =X40-X40/(1+Assumptions!$B$12) -> 54.312952
A49: Party Sampler builds are the Commerce catalog descriptions (half pan = 128 oz, full pan = 256 oz, pint = 16 oz, Texas loaf = 20 slices). Cornbread comes with 0.5 oz tallow honey butter.
A50: Quantities: 5-Alarm 2-3 and 5-6 builds are from the current Walk-In Sampler descriptions in Square. Cuban builds from the Square item descriptions (Brisket Cuban: brisket, Swiss, pickled onions; Smokin' Cuban: pork, ham, salami, jerk mayo-mustard-relish aioli, guava BBQ). Portion weights for the Cubans are estimates.

Sheet Sales & P&L
A1: Daily sales forecast and monthly P&L (3 scenarios)
A2: Base units per day are inputs (blue). Conservative and Strong scale the base by the multipliers on Assumptions.
A4: Menu item | B4: Price | C4: Base units / day (catering = per week / 5) | D4: Conservative units | E4: Strong units | G4: Revenue / day (Cons.) | H4: Revenue / day (Base) | I4: Revenue / day (Strong)
A5: 5-Alarm Sampler 2-3 | B5: =Assumptions!$B$50 -> 59.99 | C5: 14 | D5: =C5*Assumptions!$B$7 -> 9.1 | E5: =C5*Assumptions!$B$9 -> 19.6 | G5: =B5*D5 -> 545.909 | H5: =B5*C5 -> 839.86 | I5: =B5*E5 -> 1175.804
A6: 5-Alarm Sampler 5-6 | B6: =Assumptions!$B$51 -> 119.99 | C6: 3 | D6: =C6*Assumptions!$B$7 -> 1.95 | E6: =C6*Assumptions!$B$9 -> 4.2 | G6: =B6*D6 -> 233.9805 | H6: =B6*C6 -> 359.97 | I6: =B6*E6 -> 503.958
A7: Brisket Cuban | B7: =Assumptions!$B$52 -> 17.99 | C7: 22 | D7: =C7*Assumptions!$B$7 -> 14.3 | E7: =C7*Assumptions!$B$9 -> 30.8 | G7: =B7*D7 -> 257.257 | H7: =B7*C7 -> 395.78 | I7: =B7*E7 -> 554.092
A8: Smokin' Cuban | B8: =Assumptions!$B$53 -> 14.99 | C8: 25 | D8: =C8*Assumptions!$B$7 -> 16.25 | E8: =C8*Assumptions!$B$9 -> 35 | G8: =B8*D8 -> 243.5875 | H8: =B8*C8 -> 374.75 | I8: =B8*E8 -> 524.65
A9: Pre-order Brisket /lb | B9: =Assumptions!$B$54 -> 45.99 | C9: 5 | D9: =C9*Assumptions!$B$7 -> 3.25 | E9: =C9*Assumptions!$B$9 -> 7 | G9: =B9*D9 -> 149.4675 | H9: =B9*C9 -> 229.95 | I9: =B9*E9 -> 321.93
A10: Pre-order Pulled Pork /lb | B10: =Assumptions!$B$55 -> 18.99 | C10: 3 | D10: =C10*Assumptions!$B$7 -> 1.95 | E10: =C10*Assumptions!$B$9 -> 4.2 | G10: =B10*D10 -> 37.0305 | H10: =B10*C10 -> 56.97 | I10: =B10*E10 -> 79.758
A11: Pre-order Spare Ribs /rack | B11: =Assumptions!$B$56 -> 46.99 | C11: 2 | D11: =C11*Assumptions!$B$7 -> 1.3 | E11: =C11*Assumptions!$B$9 -> 2.8 | G11: =B11*D11 -> 61.087 | H11: =B11*C11 -> 93.98 | I11: =B11*E11 -> 131.572
A12: Pre-order Burnt Ends /lb | B12: =Assumptions!$B$57 -> 36.99 | C12: 2 | D12: =C12*Assumptions!$B$7 -> 1.3 | E12: =C12*Assumptions!$B$9 -> 2.8 | G12: =B12*D12 -> 48.087 | H12: =B12*C12 -> 73.98 | I12: =B12*E12 -> 103.572
A13: Pre-order Sausage /link | B13: =Assumptions!$B$58 -> 5.99 | C13: 6 | D13: =C13*Assumptions!$B$7 -> 3.9 | E13: =C13*Assumptions!$B$9 -> 8.4 | G13: =B13*D13 -> 23.361 | H13: =B13*C13 -> 35.94 | I13: =B13*E13 -> 50.316
A14: Pre-order Chicken LQ | B14: =Assumptions!$B$59 -> 7.99 | C14: 4 | D14: =C14*Assumptions!$B$7 -> 2.6 | E14: =C14*Assumptions!$B$9 -> 5.6 | G14: =B14*D14 -> 20.774 | H14: =B14*C14 -> 31.96 | I14: =B14*E14 -> 44.744
A15: Mac & Cheese 6 oz | B15: =Assumptions!$B$60 -> 5.99 | C15: 10 | D15: =C15*Assumptions!$B$7 -> 6.5 | E15: =C15*Assumptions!$B$9 -> 14 | G15: =B15*D15 -> 38.935 | H15: =B15*C15 -> 59.9 | I15: =B15*E15 -> 83.86
A16: Cowboy Beans 6 oz | B16: =Assumptions!$B$60 -> 5.99 | C16: 6 | D16: =C16*Assumptions!$B$7 -> 3.9 | E16: =C16*Assumptions!$B$9 -> 8.4 | G16: =B16*D16 -> 23.361 | H16: =B16*C16 -> 35.94 | I16: =B16*E16 -> 50.316
A17: Apple Slaw 6 oz | B17: =Assumptions!$B$60 -> 5.99 | C17: 4 | D17: =C17*Assumptions!$B$7 -> 2.6 | E17: =C17*Assumptions!$B$9 -> 5.6 | G17: =B17*D17 -> 15.574 | H17: =B17*C17 -> 23.96 | I17: =B17*E17 -> 33.544
A18: Banana Pudding | B18: =Assumptions!$B$61 -> 5.99 | C18: 12 | D18: =C18*Assumptions!$B$7 -> 7.8 | E18: =C18*Assumptions!$B$9 -> 16.8 | G18: =B18*D18 -> 46.722 | H18: =B18*C18 -> 71.88 | I18: =B18*E18 -> 100.632
A19: Fountain drink | B19: =Assumptions!$B$62 -> 2.99 | C19: 40 | D19: =C19*Assumptions!$B$7 -> 26 | E19: =C19*Assumptions!$B$9 -> 56 | G19: =B19*D19 -> 77.74 | H19: =B19*C19 -> 119.6 | I19: =B19*E19 -> 167.44
A20: Cornbread + tallow butter | B20: =Assumptions!$B$63 -> 2.99 | C20: 12 | D20: =C20*Assumptions!$B$7 -> 7.8 | E20: =C20*Assumptions!$B$9 -> 16.8 | G20: =B20*D20 -> 23.322 | H20: =B20*C20 -> 35.88 | I20: =B20*E20 -> 50.232
A21: Party Sampler Feeds 10 | B21: =Assumptions!$B$64 -> 289 | C21: 0.8 | D21: =C21*Assumptions!$B$7 -> 0.52 | E21: =C21*Assumptions!$B$9 -> 1.12 | G21: =B21*D21 -> 150.28 | H21: =B21*C21 -> 231.2 | I21: =B21*E21 -> 323.68
A22: Party Sampler Feeds 20 | B22: =Assumptions!$B$65 -> 570 | C22: 0.4 | D22: =C22*Assumptions!$B$7 -> 0.26 | E22: =C22*Assumptions!$B$9 -> 0.56 | G22: =B22*D22 -> 148.2 | H22: =B22*C22 -> 228 | I22: =B22*E22 -> 319.2
A23: Party Sampler Feeds 30 | B23: =Assumptions!$B$66 -> 825 | C23: 0.2 | D23: =C23*Assumptions!$B$7 -> 0.13 | E23: =C23*Assumptions!$B$9 -> 0.28 | G23: =B23*D23 -> 107.25 | H23: =B23*C23 -> 165 | I23: =B23*E23 -> 231
A24: Party Sampler Feeds 50 | B24: =Assumptions!$B$67 -> 1350 | C24: 0.1 | D24: =C24*Assumptions!$B$7 -> 0.065 | E24: =C24*Assumptions!$B$9 -> 0.14 | G24: =B24*D24 -> 87.75 | H24: =B24*C24 -> 135 | I24: =B24*E24 -> 189
A25: Daily sales | G25: =SUM(G5:G24) -> 2339.675 | H25: =SUM(H5:H24) -> 3599.5 | I25: =SUM(I5:I24) -> 5039.3
A26: Implied tickets / day at Seminole avg ticket | G26: =G25/Assumptions!$B$10 -> 49.993056 | H26: =H25/Assumptions!$B$10 -> 76.912393 | I26: =I25/Assumptions!$B$10 -> 107.67735
A27: Weekly sales | G27: =G25*Assumptions!$B$5 -> 11698.375 | H27: =H25*Assumptions!$B$5 -> 17997.5 | I27: =I25*Assumptions!$B$5 -> 25196.5
A28: Evening catering base: 4 Feeds-10, 2 Feeds-20, 1 Feeds-30 and 1 Feeds-50 every two weeks, picked up 2:30-7:00 pm (estimate - set your own target).
A29: Base units set so the base day (~$2,800) matches Seminole Heights Thu-Sat average ($2.1K-$2.9K/day, Sep 18-Oct 27) with walk-in à la carte removed and pre-orders added.
A31: Monthly P&L
G32: Conservative | H32: Base | I32: Strong
A33: Walk-in lunch (samplers, Cubans, sides, drinks) | G33: =(G5+G6+G7+G8+G15+G16+G17+G18+G19+G20)*Assumptions!$B$5*Assumptions!$B$6 -> 32613.3 | H33: =(H5+H6+H7+H8+H15+H16+H17+H18+H19+H20)*Assumptions!$B$5*Assumptions!$B$6 -> 50174.308 | I33: =(I5+I6+I7+I8+I15+I16+I17+I18+I19+I20)*Assumptions!$B$5*Assumptions!$B$6 -> 70244.031
A34: Pre-orders (meats by the pound, to-go window) | G34: =(G9+G10+G11+G12+G13+G14)*Assumptions!$B$5*Assumptions!$B$6 -> 7356.8215 | H34: =(H9+H10+H11+H12+H13+H14)*Assumptions!$B$5*Assumptions!$B$6 -> 11318.187 | I34: =(I9+I10+I11+I12+I13+I14)*Assumptions!$B$5*Assumptions!$B$6 -> 15845.462
A35: Evening catering pickups (Party Samplers, until 7 pm) | G35: =(G21+G22+G23+G24)*Assumptions!$B$5*Assumptions!$B$6 -> 10683.842 | H35: =(H21+H22+H23+H24)*Assumptions!$B$5*Assumptions!$B$6 -> 16436.68 | I35: =(I21+I22+I23+I24)*Assumptions!$B$5*Assumptions!$B$6 -> 23011.352
A36: Revenue | G36: =G25*Assumptions!$B$5*Assumptions!$B$6 -> 50653.964 | H36: =H25*Assumptions!$B$5*Assumptions!$B$6 -> 77929.175 | I36: =I25*Assumptions!$B$5*Assumptions!$B$6 -> 109100.85
A37: Meats (commissary transfer price) | G37: =(D5*'Menu Costing'!E40+D6*'Menu Costing'!F40+D7*'Menu Costing'!G40+D8*'Menu Costing'!H40+D9*'Menu Costing'!I40+D10*'Menu Costing'!J40+D11*'Menu Costing'!K40+D12*'Menu Costing'!L40+D13*'Menu Costing'!M40+D14*'Menu Costing'!N40+D15*'Menu Costing'!O40+D16*'Menu Costing'!P40+D17*'Menu Costing'!Q40+D18*'Menu Costing'!R40+D19*'Menu Costing'!S40+D20*'Menu Costing'!T40+D21*'Menu Costing'!U40+D22*'Menu Costing'!V40+D23*'Menu Costing'!W40+D24*'Menu Costing'!X40)*Assumptions!$B$5*Assumptions!$B$6 -> 10090.865 | H37: =(C5*'Menu Costing'!E40+C6*'Menu Costing'!F40+C7*'Menu Costing'!G40+C8*'Menu Costing'!H40+C9*'Menu Costing'!I40+C10*'Menu Costing'!J40+C11*'Menu Costing'!K40+C12*'Menu Costing'!L40+C13*'Menu Costing'!M40+C14*'Menu Costing'!N40+C15*'Menu Costing'!O40+C16*'Menu Costing'!P40+C17*'Menu Costing'!Q40+C18*'Menu Costing'!R40+C19*'Menu Costing'!S40+C20*'Menu Costing'!T40+C21*'Menu Costing'!U40+C22*'Menu Costing'!V40+C23*'Menu Costing'!W40+C24*'Menu Costing'!X40)*Assumptions!$B$5*Assumptions!$B$6 -> 15524.407 | I37: =(E5*'Menu Costing'!E40+E6*'Menu Costing'!F40+E7*'Menu Costing'!G40+E8*'Menu Costing'!H40+E9*'Menu Costing'!I40+E10*'Menu Costing'!J40+E11*'Menu Costing'!K40+E12*'Menu Costing'!L40+E13*'Menu Costing'!M40+E14*'Menu Costing'!N40+E15*'Menu Costing'!O40+E16*'Menu Costing'!P40+E17*'Menu Costing'!Q40+E18*'Menu Costing'!R40+E19*'Menu Costing'!S40+E20*'Menu Costing'!T40+E21*'Menu Costing'!U40+E22*'Menu Costing'!V40+E23*'Menu Costing'!W40+E24*'Menu Costing'!X40)*Assumptions!$B$5*Assumptions!$B$6 -> 21734.17
A38: Other food (sides, bread, deli, drinks) | G38: =(D5*'Menu Costing'!E41+D6*'Menu Costing'!F41+D7*'Menu Costing'!G41+D8*'Menu Costing'!H41+D9*'Menu Costing'!I41+D10*'Menu Costing'!J41+D11*'Menu Costing'!K41+D12*'Menu Costing'!L41+D13*'Menu Costing'!M41+D14*'Menu Costing'!N41+D15*'Menu Costing'!O41+D16*'Menu Costing'!P41+D17*'Menu Costing'!Q41+D18*'Menu Costing'!R41+D19*'Menu Costing'!S41+D20*'Menu Costing'!T41+D21*'Menu Costing'!U41+D22*'Menu Costing'!V41+D23*'Menu Costing'!W41+D24*'Menu Costing'!X41)*Assumptions!$B$5*Assumptions!$B$6 -> 5228.5623 | H38: =(C5*'Menu Costing'!E41+C6*'Menu Costing'!F41+C7*'Menu Costing'!G41+C8*'Menu Costing'!H41+C9*'Menu Costing'!I41+C10*'Menu Costing'!J41+C11*'Menu Costing'!K41+C12*'Menu Costing'!L41+C13*'Menu Costing'!M41+C14*'Menu Costing'!N41+C15*'Menu Costing'!O41+C16*'Menu Costing'!P41+C17*'Menu Costing'!Q41+C18*'Menu Costing'!R41+C19*'Menu Costing'!S41+C20*'Menu Costing'!T41+C21*'Menu Costing'!U41+C22*'Menu Costing'!V41+C23*'Menu Costing'!W41+C24*'Menu Costing'!X41)*Assumptions!$B$5*Assumptions!$B$6 -> 8043.942 | I38: =(E5*'Menu Costing'!E41+E6*'Menu Costing'!F41+E7*'Menu Costing'!G41+E8*'Menu Costing'!H41+E9*'Menu Costing'!I41+E10*'Menu Costing'!J41+E11*'Menu Costing'!K41+E12*'Menu Costing'!L41+E13*'Menu Costing'!M41+E14*'Menu Costing'!N41+E15*'Menu Costing'!O41+E16*'Menu Costing'!P41+E17*'Menu Costing'!Q41+E18*'Menu Costing'!R41+E19*'Menu Costing'!S41+E20*'Menu Costing'!T41+E21*'Menu Costing'!U41+E22*'Menu Costing'!V41+E23*'Menu Costing'!W41+E24*'Menu Costing'!X41)*Assumptions!$B$5*Assumptions!$B$6 -> 11261.519
A39: Packaging | G39: =(D5*'Menu Costing'!E42+D6*'Menu Costing'!F42+D7*'Menu Costing'!G42+D8*'Menu Costing'!H42+D9*'Menu Costing'!I42+D10*'Menu Costing'!J42+D11*'Menu Costing'!K42+D12*'Menu Costing'!L42+D13*'Menu Costing'!M42+D14*'Menu Costing'!N42+D15*'Menu Costing'!O42+D16*'Menu Costing'!P42+D17*'Menu Costing'!Q42+D18*'Menu Costing'!R42+D19*'Menu Costing'!S42+D20*'Menu Costing'!T42+D21*'Menu Costing'!U42+D22*'Menu Costing'!V42+D23*'Menu Costing'!W42+D24*'Menu Costing'!X42)*Assumptions!$B$5*Assumptions!$B$6 -> 1682.1436 | H39: =(C5*'Menu Costing'!E42+C6*'Menu Costing'!F42+C7*'Menu Costing'!G42+C8*'Menu Costing'!H42+C9*'Menu Costing'!I42+C10*'Menu Costing'!J42+C11*'Menu Costing'!K42+C12*'Menu Costing'!L42+C13*'Menu Costing'!M42+C14*'Menu Costing'!N42+C15*'Menu Costing'!O42+C16*'Menu Costing'!P42+C17*'Menu Costing'!Q42+C18*'Menu Costing'!R42+C19*'Menu Costing'!S42+C20*'Menu Costing'!T42+C21*'Menu Costing'!U42+C22*'Menu Costing'!V42+C23*'Menu Costing'!W42+C24*'Menu Costing'!X42)*Assumptions!$B$5*Assumptions!$B$6 -> 2587.9133 | I39: =(E5*'Menu Costing'!E42+E6*'Menu Costing'!F42+E7*'Menu Costing'!G42+E8*'Menu Costing'!H42+E9*'Menu Costing'!I42+E10*'Menu Costing'!J42+E11*'Menu Costing'!K42+E12*'Menu Costing'!L42+E13*'Menu Costing'!M42+E14*'Menu Costing'!N42+E15*'Menu Costing'!O42+E16*'Menu Costing'!P42+E17*'Menu Costing'!Q42+E18*'Menu Costing'!R42+E19*'Menu Costing'!S42+E20*'Menu Costing'!T42+E21*'Menu Costing'!U42+E22*'Menu Costing'!V42+E23*'Menu Costing'!W42+E24*'Menu Costing'!X42)*Assumptions!$B$5*Assumptions!$B$6 -> 3623.0786
A40: Waste / comps | G40: =(G37+G38)*Assumptions!$B$99 -> 459.58281 | H40: =(H37+H38)*Assumptions!$B$99 -> 707.05048 | I40: =(I37+I38)*Assumptions!$B$99 -> 989.87067
A41: Total cost of goods | G41: =SUM(G37:G40) -> 17461.154 | H41: =SUM(H37:H40) -> 26863.313 | I41: =SUM(I37:I40) -> 37608.638
A42: COGS % of sales | G42: =IF(G36=0,0,G41/G36) -> 0.34471446 | H42: =IF(H36=0,0,H41/H36) -> 0.34471446 | I42: =IF(I36=0,0,I41/I36) -> 0.34471446
A43: Gross profit | G43: =G36-G41 -> 33192.81 | H43: =H36-H41 -> 51065.862 | I43: =I36-I41 -> 71492.207
A44: GM salary | G44: =Assumptions!$B$69/12 -> 5000 | H44: =Assumptions!$B$69/12 -> 5000 | I44: =Assumptions!$B$69/12 -> 5000
A45: Hourly crew (incl. early smoker start) | G45: =(Assumptions!$B$70*Assumptions!$B$71+Assumptions!$B$76)*Assumptions!$B$72*Assumptions!$B$5*Assumptions!$B$6 -> 7794 | H45: =(Assumptions!$B$70*Assumptions!$B$71+Assumptions!$B$76)*Assumptions!$B$72*Assumptions!$B$5*Assumptions!$B$6 -> 7794 | I45: =(Assumptions!$B$70*Assumptions!$B$71+Assumptions!$B$76)*Assumptions!$B$72*Assumptions!$B$5*Assumptions!$B$6 -> 7794
A46: Evening catering pickup shift | G46: =Assumptions!$B$74*Assumptions!$B$75*Assumptions!$B$72*Assumptions!$B$5*Assumptions!$B$6 -> 1732 | H46: =Assumptions!$B$74*Assumptions!$B$75*Assumptions!$B$72*Assumptions!$B$5*Assumptions!$B$6 -> 1732 | I46: =Assumptions!$B$74*Assumptions!$B$75*Assumptions!$B$72*Assumptions!$B$5*Assumptions!$B$6 -> 1732
A47: Payroll taxes + WC | G47: =(G44+G45+G46)*Assumptions!$B$73 -> 1597.86 | H47: =(H44+H45+H46)*Assumptions!$B$73 -> 1597.86 | I47: =(I44+I45+I46)*Assumptions!$B$73 -> 1597.86
A48: Total labor | G48: =SUM(G44:G47) -> 16123.86 | H48: =SUM(H44:H47) -> 16123.86 | I48: =SUM(I44:I47) -> 16123.86
A49: Labor % of sales | G49: =IF(G36=0,0,G48/G36) -> 0.31831389 | H49: =IF(H36=0,0,H48/H36) -> 0.20690403 | I49: =IF(I36=0,0,I48/I36) -> 0.14778859
A50: Prime cost % (COGS + labor) | G50: =IF(G36=0,0,(G41+G48)/G36) -> 0.66302834 | H50: =IF(H36=0,0,(H41+H48)/H36) -> 0.55161848 | I50: =IF(I36=0,0,(I41+I48)/I36) -> 0.49250305
A51: Rent | G51: =Assumptions!$B$84 -> 6000 | H51: =Assumptions!$B$84 -> 6000 | I51: =Assumptions!$B$84 -> 6000
A52: NNN / CAM | G52: =Assumptions!$B$85 -> 1500 | H52: =Assumptions!$B$85 -> 1500 | I52: =Assumptions!$B$85 -> 1500
A53: Utilities | G53: =Assumptions!$B$86 -> 1800 | H53: =Assumptions!$B$86 -> 1800 | I53: =Assumptions!$B$86 -> 1800
A54: Total occupancy | G54: =SUM(G51:G53) -> 9300 | H54: =SUM(H51:H53) -> 9300 | I54: =SUM(I51:I53) -> 9300
A55: Card processing | G55: =G36*Assumptions!$B$97 -> 1468.9649 | H55: =H36*Assumptions!$B$97 -> 2259.9461 | I55: =I36*Assumptions!$B$97 -> 3163.9245
A56: Marketing | G56: =G36*Assumptions!$B$98 -> 1013.0793 | H56: =H36*Assumptions!$B$98 -> 1558.5835 | I56: =I36*Assumptions!$B$98 -> 2182.0169
A57: Insurance | G57: =Assumptions!$B$87 -> 650 | H57: =Assumptions!$B$87 -> 650 | I57: =Assumptions!$B$87 -> 650
A58: Square software / online ordering | G58: =Assumptions!$B$88 -> 150 | H58: =Assumptions!$B$88 -> 150 | I58: =Assumptions!$B$88 -> 150
A59: Internet + phone | G59: =Assumptions!$B$89 -> 200 | H59: =Assumptions!$B$89 -> 200 | I59: =Assumptions!$B$89 -> 200
A60: Towels / linens | G60: =Assumptions!$B$90 -> 650 | H60: =Assumptions!$B$90 -> 650 | I60: =Assumptions!$B$90 -> 650
A61: Pest control | G61: =Assumptions!$B$91 -> 100 | H61: =Assumptions!$B$91 -> 100 | I61: =Assumptions!$B$91 -> 100
A62: Trash + grease | G62: =Assumptions!$B$92 -> 350 | H62: =Assumptions!$B$92 -> 350 | I62: =Assumptions!$B$92 -> 350
A63: Repairs + maintenance | G63: =Assumptions!$B$93 -> 500 | H63: =Assumptions!$B$93 -> 500 | I63: =Assumptions!$B$93 -> 500
A64: Bookkeeping / accounting | G64: =Assumptions!$B$94 -> 500 | H64: =Assumptions!$B$94 -> 500 | I64: =Assumptions!$B$94 -> 500
A65: On-site smoker wood / pellets | G65: =Assumptions!$B$15*Assumptions!$B$77*Assumptions!$B$5*Assumptions!$B$6 -> 324.75 | H65: =Assumptions!$B$15*Assumptions!$B$77*Assumptions!$B$5*Assumptions!$B$6 -> 324.75 | I65: =Assumptions!$B$15*Assumptions!$B$77*Assumptions!$B$5*Assumptions!$B$6 -> 324.75
A66: Licenses + permits | G66: =Assumptions!$B$95 -> 100 | H66: =Assumptions!$B$95 -> 100 | I66: =Assumptions!$B$95 -> 100
A67: Total other operating | G67: =SUM(G55:G66) -> 6006.7942 | H67: =SUM(H55:H66) -> 7343.2796 | I67: =SUM(I55:I66) -> 8870.6914
A68: Store EBITDA (before investor return, debt, depreciation) | G68: =G43-G48-G54-G67 -> 1762.156 | H68: =H43-H48-H54-H67 -> 18298.722 | I68: =I43-I48-I54-I67 -> 37197.655
A69: EBITDA margin | G69: =IF(G36=0,0,G68/G36) -> 0.034788116 | H69: =IF(H36=0,0,H68/H36) -> 0.23481222 | I69: =IF(I36=0,0,I68/I36) -> 0.34094745
A70: Annual store EBITDA | G70: =G68*12 -> 21145.872 | H70: =H68*12 -> 219584.67 | I70: =I68*12 -> 446371.86
A72: Memo: commissary profit from this store (meat markup), monthly | G72: =G37-G37/(1+Assumptions!$B$12) -> 2018.173 | H72: =H37-H37/(1+Assumptions!$B$12) -> 3104.8815 | I72: =I37-I37/(1+Assumptions!$B$12) -> 4346.8341
A73: Memo: combined Station House profit (store EBITDA + commissary markup) | G73: =G68+G72 -> 3780.329 | H73: =H68+H72 -> 21403.604 | I73: =I68+I72 -> 41544.489
A74: Payback on startup cost (months, store EBITDA only) | G74: =IF(G68<1000,"Not at this volume",'Startup Budget'!$F$50/G68) -> 264.57017 | H74: =IF(H68<1000,"Not at this volume",'Startup Budget'!$F$50/H68) -> 25.477949 | I74: =IF(I68<1000,"Not at this volume",'Startup Budget'!$F$50/I68) -> 12.533422

Sheet Break-Even
A1: Break-even
A2: Fixed costs divided by contribution margin. Uses the Base scenario cost structure.
A4: Fixed monthly costs
A5: Labor (GM + crew + payroll taxes) | B5: ='Sales & P&L'!$H$48 -> 16123.86 | D5: Treated as fixed: a lunch-only crew is scheduled the same every day.
A6: Occupancy (rent, NNN, utilities) | B6: ='Sales & P&L'!$H$54 -> 9300
A7: Fixed operating (insurance, software, linens, repairs, etc.) | B7: ='Sales & P&L'!$H$67-'Sales & P&L'!$H$55-'Sales & P&L'!$H$56 -> 3524.75
A8: Total fixed costs per month | B8: =B5+B6+B7 -> 28948.61
A10: Variable costs (% of sales, Base mix)
A11: Cost of goods % | B11: ='Sales & P&L'!$H$41/'Sales & P&L'!$H$36 -> 0.34471446
A12: Card processing % | B12: =Assumptions!$B$97 -> 0.029
A13: Marketing % | B13: =Assumptions!$B$98 -> 0.02
A14: Contribution margin % | B14: =1-B11-B12-B13 -> 0.60628554
A16: Break-even sales
A17: Break-even sales per month | B17: =B8/B14 -> 47747.485
A18: Break-even sales per week | B18: =B17/Assumptions!$B$6 -> 11027.133 | D18: Compare: Anthony's rule of thumb for retail is ~$10K/week to be worth opening.
A19: Break-even sales per day open | B19: =B18/Assumptions!$B$5 -> 2205.4266
A20: Break-even tickets per day (at $46.80 avg ticket) | B20: =B19/Assumptions!$B$10 -> 47.124499
A21: Same thing in 5-Alarm 2-3 Samplers per day | B21: =B19/Assumptions!$B$50 -> 36.763237 | D21: If every dollar came from 2-3 samplers - a way to picture the number.
A22: Base-scenario daily sales | B22: ='Sales & P&L'!$H$25 -> 3599.5
A23: Cushion: base day above break-even | B23: =B22/B19-1 -> 0.63211057
A25: Break-even including an investor return
A26: Target investor cash return (annual % of startup cost) | B26: 0.2 | D26: Input. Investor split is undecided; 20%/yr = 5-year simple payback.
A27: Investor return per month | B27: ='Startup Budget'!$F$50*B26/12 -> 7770.2319
A28: Break-even sales per day incl. investor return | B28: =(B8+B27)/B14/Assumptions!$B$6/Assumptions!$B$5 -> 2797.3954

Sheet Startup Budget
A1: Startup budget: raw shell (1st gen) vs former restaurant (2nd gen)
A2: Equipment priced new from online dealers (Oct 2026); expect 10-20% off list. A 2nd-generation space already has a hood, grease trap, plumbing and often a walk-in, so build-out drops sharply.
A4: Category | B4: Item | C4: Model / spec | D4: Qty | E4: Unit price | F4: 1st gen (raw shell) | G4: 2nd gen (former restaurant) | I4: Source / note
A5: Cooking | B5: Double-stack combi oven (2 ovens) | C5: Rational iCombi Pro 6-full, electric 208/240V 3-ph, 42" x 41" | D5: 2 | E5: 22656 | F5: =D5*E5 -> 45312 | G5: =F5 -> 45312 | I5: WebstaurantStore list $22,656 each (login price lower). 62A each - needs 3-phase service.
A6: Cooking | B6: Combi stacking kit | C6: Rational Combi-Duo 60.76.575 | D6: 1 | E6: 1300 | F6: =D6*E6 -> 1300 | G6: =F6 -> 1300 | I6: CA$1,715 (Chef Supplies); US price not found - estimate.
A7: Cooking | B7: Cook & hold cabinets (stacked) | C7: Alto-Shaam 1200-TH, 240 lb capacity, 208-240V 1-ph | D7: 2 | E7: 12533 | F7: =D7*E7 -> 25066 | G7: =F7 -> 25066 | I7: KaTom $12,532.74 each; stacked to save line space. 1000-TH/I-QS is $10,726 if smaller works.
A8: Cooking | B8: On-site smoker (daily fresh chicken) | C8: Cookshack FEC120 pellet smoker, 120V, 46.5" x 35", ~30 whole chickens/load | D8: 1 | E8: 11800 | F8: =D8*E8 -> 11800 | G8: =F8 -> 11800 | I8: KaTom $11,800; cULus listed. Goes under the Type I hood - confirm with the fire inspector.
A9: Cooking | B9: Tilting steam kettle, 20 gal | C9: Vulcan K20ETT tabletop, electric 208V 3-ph | D9: 1 | E9: 20014 | F9: =D9*E9 -> 20014 | G9: =F9 -> 20014 | I9: KaTom $20,014. Floor model K20ELT $29,481. Used Cleveland KEL20T $4,497 but 480V.
A10: Cooking | B10: Griddle + 2-burner range (no fryer) | C10: Vulcan 36S-2B24GT: 24" griddle, 2 burners, oven base, nat gas, 36" x 34" | D10: 1 | E10: 9132 | F10: =D10*E10 -> 9132 | G10: =F10 -> 9132 | I10: KaTom $9,132 (list $22,183).
A11: Cooking | B11: Cuban / sandwich press | C11: Waring WPG300 double, grooved cast iron, 240V | D11: 2 | E11: 1015 | F11: =D11*E11 -> 2030 | G11: =F11 -> 2030 | I11: KaTom $1,015 each; used $475 at City Food Equipment.
A12: Service line | B12: Carving station w/ 2 heat lamps | C12: Hatco DCSB400-3624-2, 36" x 24" board | D12: 1 | E12: 3994 | F12: =D12*E12 -> 3994 | G12: =F12 -> 3994 | I12: City Food Equipment $3,994.
A13: Service line | B13: 4-well hot food table + cold rail | C13: Electric 4-well + sneeze guard | D13: 1 | E13: 2800 | F13: =D13*E13 -> 2800 | G13: =F13 -> 2800 | I13: Estimate - no sourced price.
A14: Service line | B14: To-go heated pickup shelf | C14: Heated shelf / pass-thru, 3 tier | D14: 1 | E14: 1800 | F14: =D14*E14 -> 1800 | G14: =F14 -> 1800 | I14: Estimate.
A15: Refrigeration | B15: Walk-in cooler 8 x 10 | C15: Imperial Brown IB810C | D15: 1 | E15: 20886 | F15: =D15*E15 -> 20886 | G15: 0 | I15: KaTom $20,886. 2nd gen: Assumes the space has a usable walk-in.
A16: Refrigeration | B16: Walk-in install | C16: Set, refrigeration line, electrical | D16: 1 | E16: 4000 | F16: =D16*E16 -> 4000 | G16: 2500 | I16: Estimate. 2nd gen: Service / re-gas existing walk-in (estimate).
A17: Refrigeration | B17: Sandwich prep cooler | C17: 48"-60" refrigerated prep table | D17: 1 | E17: 3384 | F17: =D17*E17 -> 3384 | G17: =F17 -> 3384 | I17: Top of $1,649-$3,384 range (The Restaurant Warehouse).
A18: Refrigeration | B18: Reach-in / drink cooler | C18: True T-49 2-section | D18: 1 | E18: 7491 | F18: =D18*E18 -> 7491 | G18: =F18 -> 7491 | I18: KaTom $7,491.
A19: Refrigeration | B19: Ice machine + bin | C19: Manitowoc IRP0500W, 500 lb/day, 365 lb bin | D19: 1 | E19: 6395 | F19: =D19*E19 -> 6395 | G19: =F19 -> 6395 | I19: HVAC Pro Sales $6,395 (W = water-cooled; confirm).
A20: Sinks & prep | B20: 3-compartment sink | C20: Regency 72.5" 16-ga | D20: 1 | E20: 569 | F20: =D20*E20 -> 569 | G20: 0 | I20: WebstaurantStore listing (unconfirmed). 2nd gen: Usually in place.
A21: Sinks & prep | B21: Hand sinks | C21: Advance Tabco 7-PS-EC-SP-X | D21: 3 | E21: 361 | F21: =D21*E21 -> 1083 | G21: 0 | I21: KaTom $361 each. 2nd gen: Usually in place.
A22: Sinks & prep | B22: Prep sink + mop sink | D22: 1 | E22: 900 | F22: =D22*E22 -> 900 | G22: 0 | I22: Estimate. 2nd gen: Usually in place.
A23: Sinks & prep | B23: Stainless prep tables 30 x 60 | C23: Steelton 16-ga | D23: 2 | E23: 189 | F23: =D23*E23 -> 378 | G23: =F23 -> 378 | I23: WebstaurantStore $189 each.
A24: Sinks & prep | B24: Shelving (dry storage + walk-in) | C24: NSF wire shelving units | D24: 8 | E24: 180 | F24: =D24*E24 -> 1440 | G24: =F24 -> 1440 | I24: Estimate.
A25: Ventilation | B25: Type I hood, 16 ft, installed | C25: Over smoker, griddle, kettle, combi | D25: 16 | E25: 1100 | F25: =D25*E25 -> 17600 | G25: 9500 | I25: $950-$1,200 per linear ft installed (Ambient Edge); national, not FL-specific. 2nd gen: Reuse existing hood and extend ~4 ft for the smoker, re-balance (estimate).
A26: Ventilation | B26: Fire suppression | C26: ANSUL R-102, 16 ft hood (extra nozzles for smoker) | D26: 1 | E26: 12000 | F26: =D26*E26 -> 12000 | G26: 1500 | I26: ThePricer ~$10,419 for 10 ft hardware + install; +~$1,600 estimate for 16 ft. Before permits. 2nd gen: Recertify / re-nozzle existing system (estimate).
A27: Front of house | B27: Square POS register + kiosk + 2 KDS | C27: Register $1,799, kiosk ~$1,500, KDS $900 x2 | D27: 1 | E27: 5099 | F27: =D27*E27 -> 5099 | G27: =F27 -> 5099 | I27: UpMenu May 2026 Square pricing article; kiosk estimate.
A28: Front of house | B28: Tables, chairs, window bar, stools | C28: 6 four-tops, 24 chairs, bar, 8 stools | D28: 1 | E28: 8500 | F28: =D28*E28 -> 8500 | G28: =F28 -> 8500 | I28: Estimate.
A29: Front of house | B29: 5-Alarm effect: beacon, siren, controller, brass bell | C29: Feniex light bar + controller + siren + bell | D29: 1 | E29: 3550 | F29: =D29*E29 -> 3550 | G29: =F29 -> 3550 | I29: Feniex: light bar up to $1,899, controller up to $1,099, siren up to $299; bell estimate $250.
A30: Front of house | B30: Signage, logo sign, fire pole, decor | C30: Incl. helmet shelf + bunker gear display | D30: 1 | E30: 13500 | F30: =D30*E30 -> 13500 | G30: =F30 -> 13500 | I30: Estimate; used turnout gear and helmets run ~$100-$400 per piece.
A31: Smallwares | B31: Smallwares (pans, knives, boards, cambros) | D31: 1 | E31: 8000 | F31: =D31*E31 -> 8000 | G31: =F31 -> 8000 | I31: Estimate - no sourced figure.
B32: Equipment subtotal | F32: =SUM(F5:F31) -> 238023 | G32: =SUM(G5:G31) -> 194485
A34: Build-out, soft costs and pre-opening
A35: Build-out | B35: Tenant improvements (walls, floors, plumbing, electrical, restrooms) | C35: $/sq ft x 1,500 | D35: 1500 | E35: 175 | F35: =D35*E35 -> 262500 | G35: =D35*60 -> 90000 | I35: 1st gen: raw shell restaurant build-outs commonly run $150-$300/sf (estimate). 2nd gen: refresh finishes, minor plumbing/electrical at ~$60/sf (estimate). A landlord TI allowance reduces either.
A36: Build-out | B36: 3-phase electrical service upgrade | D36: 1 | E36: 0 | F36: =D36*E36 -> 0 | G36: 8000 | I36: 1st gen: included in TI. 2nd gen: combi + kettle need 3-phase; budget an upgrade if the space lacks it (estimate).
A37: Build-out | B37: Grease interceptor | D37: 1 | E37: 15000 | F37: =D37*E37 -> 15000 | G37: 500 | I37: 1st gen: new in-ground interceptor (estimate). 2nd gen: existing - pump and inspect.
A38: Soft costs | B38: Architect, engineering, permits, impact fees | D38: 1 | E38: 25000 | F38: =D38*E38 -> 25000 | G38: 12000 | I38: Estimate. 2nd gen is often a change-of-use or alteration permit only.
A39: Pre-opening | B39: Security deposit + first month (rent + NNN) | D39: 2 | E39: =Assumptions!$B$84+Assumptions!$B$85 -> 7500 | F39: =D39*E39 -> 15000 | G39: =F39 -> 15000 | I39: Formula: 2 x (rent + NNN).
A40: Pre-opening | B40: Pre-opening labor (training, 2 weeks) | D40: 1 | E40: 8000 | F40: =D40*E40 -> 8000 | G40: =F40 -> 8000 | I40: Estimate.
A41: Pre-opening | B41: Opening inventory (non-meat) + packaging | D41: 1 | E41: 4000 | F41: =D41*E41 -> 4000 | G41: =F41 -> 4000 | I41: Estimate.
A42: Pre-opening | B42: Grand opening marketing | D42: 1 | E42: 5000 | F42: =D42*E42 -> 5000 | G42: =F42 -> 5000 | I42: Estimate.
A43: Pre-opening | B43: Working capital reserve (3 months fixed costs) | D43: 1 | E43: ='Break-Even'!$B$8*3 -> 86845.83 | F43: =D43*E43 -> 86845.83 | G43: =F43 -> 86845.83 | I43: Formula: 3 x fixed monthly costs from Break-Even.
B44: Build-out and pre-opening subtotal | F44: =SUM(F35:F43) -> 421345.83 | G44: =SUM(G35:G43) -> 229345.83
B46: Contingency | E46: 0.1 | F46: =(F32+F44)*$E$46 -> 65936.883 | G46: =(G32+G44)*$E$46 -> 42383.083
B47: TOTAL STARTUP COST | F47: =F32+F44+F46 -> 725305.71 | G47: =G32+G44+G46 -> 466213.91
B48: 2nd gen saves | G48: =F47-G47 -> 259091.8
B50: Startup cost used in the plan (per Assumptions: 1 = 1st gen, 2 = 2nd gen) | F50: =IF(Assumptions!$B$82=1,F47,G47) -> 466213.91

Sheet Prep List
A1: Daily prep list (par levels)
A2: Forecast use = menu-item quantities x forecast units, plus the prep buffer. Pick the scenario column that matches the day.
A4: Component | B4: Unit | C4: Conservative day | D4: Base day | E4: Strong day | F4: Base: prep as | G4: How / when | H4: Prep unit
A5: Brisket (sliced) | B5: cooked lb | C5: =('Menu Costing'!E5*'Sales & P&L'!D5+'Menu Costing'!F5*'Sales & P&L'!D6+'Menu Costing'!G5*'Sales & P&L'!D7+'Menu Costing'!I5*'Sales & P&L'!D9+'Menu Costing'!U5*'Sales & P&L'!D21+'Menu Costing'!V5*'Sales & P&L'!D22+'Menu Costing'!W5*'Sales & P&L'!D23+'Menu Costing'!X5*'Sales & P&L'!D24)*(1+Assumptions!$B$48) -> 13.013 | D5: =('Menu Costing'!E5*'Sales & P&L'!C5+'Menu Costing'!F5*'Sales & P&L'!C6+'Menu Costing'!G5*'Sales & P&L'!C7+'Menu Costing'!I5*'Sales & P&L'!C9+'Menu Costing'!U5*'Sales & P&L'!C21+'Menu Costing'!V5*'Sales & P&L'!C22+'Menu Costing'!W5*'Sales & P&L'!C23+'Menu Costing'!X5*'Sales & P&L'!C24)*(1+Assumptions!$B$48) -> 20.02 | E5: =('Menu Costing'!E5*'Sales & P&L'!E5+'Menu Costing'!F5*'Sales & P&L'!E6+'Menu Costing'!G5*'Sales & P&L'!E7+'Menu Costing'!I5*'Sales & P&L'!E9+'Menu Costing'!U5*'Sales & P&L'!E21+'Menu Costing'!V5*'Sales & P&L'!E22+'Menu Costing'!W5*'Sales & P&L'!E23+'Menu Costing'!X5*'Sales & P&L'!E24)*(1+Assumptions!$B$48) -> 28.028 | F5: =D5/(Assumptions!$B$39*Assumptions!$B$46) -> 2.86 | G5: Pull vac-packs from walk-in 8:30; combi reheat to 165F, hold in Alto-Shaam. Slice to order only. | H5: packers
A6: Pulled pork | B6: cooked lb | C6: =('Menu Costing'!E6*'Sales & P&L'!D5+'Menu Costing'!F6*'Sales & P&L'!D6+'Menu Costing'!H6*'Sales & P&L'!D8+'Menu Costing'!J6*'Sales & P&L'!D10+'Menu Costing'!U6*'Sales & P&L'!D21+'Menu Costing'!V6*'Sales & P&L'!D22+'Menu Costing'!W6*'Sales & P&L'!D23+'Menu Costing'!X6*'Sales & P&L'!D24)*(1+Assumptions!$B$48) -> 13.897813 | D6: =('Menu Costing'!E6*'Sales & P&L'!C5+'Menu Costing'!F6*'Sales & P&L'!C6+'Menu Costing'!H6*'Sales & P&L'!C8+'Menu Costing'!J6*'Sales & P&L'!C10+'Menu Costing'!U6*'Sales & P&L'!C21+'Menu Costing'!V6*'Sales & P&L'!C22+'Menu Costing'!W6*'Sales & P&L'!C23+'Menu Costing'!X6*'Sales & P&L'!C24)*(1+Assumptions!$B$48) -> 21.38125 | E6: =('Menu Costing'!E6*'Sales & P&L'!E5+'Menu Costing'!F6*'Sales & P&L'!E6+'Menu Costing'!H6*'Sales & P&L'!E8+'Menu Costing'!J6*'Sales & P&L'!E10+'Menu Costing'!U6*'Sales & P&L'!E21+'Menu Costing'!V6*'Sales & P&L'!E22+'Menu Costing'!W6*'Sales & P&L'!E23+'Menu Costing'!X6*'Sales & P&L'!E24)*(1+Assumptions!$B$48) -> 29.93375 | F6: =D6 -> 21.38125 | G6: Reheat in combi with jus, hold in Alto-Shaam; pull for Cubans and samplers. | H6: lb cooked
A7: Burnt ends | B7: cooked lb | C7: =('Menu Costing'!L7*'Sales & P&L'!D12)*(1+Assumptions!$B$48) -> 1.43 | D7: =('Menu Costing'!L7*'Sales & P&L'!C12)*(1+Assumptions!$B$48) -> 2.2 | E7: =('Menu Costing'!L7*'Sales & P&L'!E12)*(1+Assumptions!$B$48) -> 3.08 | F7: =D7 -> 2.2 | G7: Pre-orders only: reheat and glaze to order. | H7: lb cooked
A8: Spare rib (bone) | B8: bone | C8: =('Menu Costing'!E8*'Sales & P&L'!D5+'Menu Costing'!F8*'Sales & P&L'!D6+'Menu Costing'!K8*'Sales & P&L'!D11+'Menu Costing'!U8*'Sales & P&L'!D21+'Menu Costing'!V8*'Sales & P&L'!D22+'Menu Costing'!W8*'Sales & P&L'!D23+'Menu Costing'!X8*'Sales & P&L'!D24)*(1+Assumptions!$B$48) -> 61.204 | D8: =('Menu Costing'!E8*'Sales & P&L'!C5+'Menu Costing'!F8*'Sales & P&L'!C6+'Menu Costing'!K8*'Sales & P&L'!C11+'Menu Costing'!U8*'Sales & P&L'!C21+'Menu Costing'!V8*'Sales & P&L'!C22+'Menu Costing'!W8*'Sales & P&L'!C23+'Menu Costing'!X8*'Sales & P&L'!C24)*(1+Assumptions!$B$48) -> 94.16 | E8: =('Menu Costing'!E8*'Sales & P&L'!E5+'Menu Costing'!F8*'Sales & P&L'!E6+'Menu Costing'!K8*'Sales & P&L'!E11+'Menu Costing'!U8*'Sales & P&L'!E21+'Menu Costing'!V8*'Sales & P&L'!E22+'Menu Costing'!W8*'Sales & P&L'!E23+'Menu Costing'!X8*'Sales & P&L'!E24)*(1+Assumptions!$B$48) -> 131.824 | F8: =D8/Assumptions!$B$43 -> 7.8466667 | G8: Reheat racks in combi, hold wrapped; cut to bones at cutting station. | H8: racks
A9: Chicken leg quarter | B9: each | C9: =('Menu Costing'!E9*'Sales & P&L'!D5+'Menu Costing'!F9*'Sales & P&L'!D6+'Menu Costing'!N9*'Sales & P&L'!D14+'Menu Costing'!U9*'Sales & P&L'!D21+'Menu Costing'!V9*'Sales & P&L'!D22+'Menu Costing'!W9*'Sales & P&L'!D23+'Menu Costing'!X9*'Sales & P&L'!D24)*(1+Assumptions!$B$48) -> 22.9515 | D9: =('Menu Costing'!E9*'Sales & P&L'!C5+'Menu Costing'!F9*'Sales & P&L'!C6+'Menu Costing'!N9*'Sales & P&L'!C14+'Menu Costing'!U9*'Sales & P&L'!C21+'Menu Costing'!V9*'Sales & P&L'!C22+'Menu Costing'!W9*'Sales & P&L'!C23+'Menu Costing'!X9*'Sales & P&L'!C24)*(1+Assumptions!$B$48) -> 35.31 | E9: =('Menu Costing'!E9*'Sales & P&L'!E5+'Menu Costing'!F9*'Sales & P&L'!E6+'Menu Costing'!N9*'Sales & P&L'!E14+'Menu Costing'!U9*'Sales & P&L'!E21+'Menu Costing'!V9*'Sales & P&L'!E22+'Menu Costing'!W9*'Sales & P&L'!E23+'Menu Costing'!X9*'Sales & P&L'!E24)*(1+Assumptions!$B$48) -> 49.434 | F9: =D9 -> 35.31 | G9: Smoked fresh daily in the store smoker: load 7:30, ready ~10:30, into Alto-Shaam. | H9: pieces
A10: Jalapeno cheddar sausage | B10: link | C10: =('Menu Costing'!E10*'Sales & P&L'!D5+'Menu Costing'!F10*'Sales & P&L'!D6+'Menu Costing'!M10*'Sales & P&L'!D13+'Menu Costing'!U10*'Sales & P&L'!D21+'Menu Costing'!V10*'Sales & P&L'!D22+'Menu Costing'!W10*'Sales & P&L'!D23+'Menu Costing'!X10*'Sales & P&L'!D24)*(1+Assumptions!$B$48) -> 26.312 | D10: =('Menu Costing'!E10*'Sales & P&L'!C5+'Menu Costing'!F10*'Sales & P&L'!C6+'Menu Costing'!M10*'Sales & P&L'!C13+'Menu Costing'!U10*'Sales & P&L'!C21+'Menu Costing'!V10*'Sales & P&L'!C22+'Menu Costing'!W10*'Sales & P&L'!C23+'Menu Costing'!X10*'Sales & P&L'!C24)*(1+Assumptions!$B$48) -> 40.48 | E10: =('Menu Costing'!E10*'Sales & P&L'!E5+'Menu Costing'!F10*'Sales & P&L'!E6+'Menu Costing'!M10*'Sales & P&L'!E13+'Menu Costing'!U10*'Sales & P&L'!E21+'Menu Costing'!V10*'Sales & P&L'!E22+'Menu Costing'!W10*'Sales & P&L'!E23+'Menu Costing'!X10*'Sales & P&L'!E24)*(1+Assumptions!$B$48) -> 56.672 | F10: =D10 -> 40.48 | G10: Reheat in combi, hold. | H10: links
A11: Mac & cheese | B11: oz | C11: =('Menu Costing'!E11*'Sales & P&L'!D5+'Menu Costing'!F11*'Sales & P&L'!D6+'Menu Costing'!O11*'Sales & P&L'!D15+'Menu Costing'!U11*'Sales & P&L'!D21+'Menu Costing'!V11*'Sales & P&L'!D22+'Menu Costing'!W11*'Sales & P&L'!D23+'Menu Costing'!X11*'Sales & P&L'!D24)*(1+Assumptions!$B$48) -> 411.268 | D11: =('Menu Costing'!E11*'Sales & P&L'!C5+'Menu Costing'!F11*'Sales & P&L'!C6+'Menu Costing'!O11*'Sales & P&L'!C15+'Menu Costing'!U11*'Sales & P&L'!C21+'Menu Costing'!V11*'Sales & P&L'!C22+'Menu Costing'!W11*'Sales & P&L'!C23+'Menu Costing'!X11*'Sales & P&L'!C24)*(1+Assumptions!$B$48) -> 632.72 | E11: =('Menu Costing'!E11*'Sales & P&L'!E5+'Menu Costing'!F11*'Sales & P&L'!E6+'Menu Costing'!O11*'Sales & P&L'!E15+'Menu Costing'!U11*'Sales & P&L'!E21+'Menu Costing'!V11*'Sales & P&L'!E22+'Menu Costing'!W11*'Sales & P&L'!E23+'Menu Costing'!X11*'Sales & P&L'!E24)*(1+Assumptions!$B$48) -> 885.808 | F11: =D11/'Sides & Ingredients'!$E$25 -> 2.4715625 | G11: Kettle, 9:00. Hold in hot well; second batch at 12:00 if Strong. | H11: batches (2 gal)
A12: Cowboy beans | B12: oz | C12: =('Menu Costing'!E12*'Sales & P&L'!D5+'Menu Costing'!F12*'Sales & P&L'!D6+'Menu Costing'!P12*'Sales & P&L'!D16+'Menu Costing'!U12*'Sales & P&L'!D21+'Menu Costing'!V12*'Sales & P&L'!D22+'Menu Costing'!W12*'Sales & P&L'!D23+'Menu Costing'!X12*'Sales & P&L'!D24)*(1+Assumptions!$B$48) -> 231.66 | D12: =('Menu Costing'!E12*'Sales & P&L'!C5+'Menu Costing'!F12*'Sales & P&L'!C6+'Menu Costing'!P12*'Sales & P&L'!C16+'Menu Costing'!U12*'Sales & P&L'!C21+'Menu Costing'!V12*'Sales & P&L'!C22+'Menu Costing'!W12*'Sales & P&L'!C23+'Menu Costing'!X12*'Sales & P&L'!C24)*(1+Assumptions!$B$48) -> 356.4 | E12: =('Menu Costing'!E12*'Sales & P&L'!E5+'Menu Costing'!F12*'Sales & P&L'!E6+'Menu Costing'!P12*'Sales & P&L'!E16+'Menu Costing'!U12*'Sales & P&L'!E21+'Menu Costing'!V12*'Sales & P&L'!E22+'Menu Costing'!W12*'Sales & P&L'!E23+'Menu Costing'!X12*'Sales & P&L'!E24)*(1+Assumptions!$B$48) -> 498.96 | F12: =D12/'Sides & Ingredients'!$E$38 -> 1.0482353 | G12: Kettle after mac. Hold in hot well. | H12: batches
A13: Apple coleslaw | B13: oz | C13: =('Menu Costing'!Q13*'Sales & P&L'!D17+'Menu Costing'!U13*'Sales & P&L'!D21+'Menu Costing'!V13*'Sales & P&L'!D22+'Menu Costing'!W13*'Sales & P&L'!D23+'Menu Costing'!X13*'Sales & P&L'!D24)*(1+Assumptions!$B$48) -> 108.68 | D13: =('Menu Costing'!Q13*'Sales & P&L'!C17+'Menu Costing'!U13*'Sales & P&L'!C21+'Menu Costing'!V13*'Sales & P&L'!C22+'Menu Costing'!W13*'Sales & P&L'!C23+'Menu Costing'!X13*'Sales & P&L'!C24)*(1+Assumptions!$B$48) -> 167.2 | E13: =('Menu Costing'!Q13*'Sales & P&L'!E17+'Menu Costing'!U13*'Sales & P&L'!E21+'Menu Costing'!V13*'Sales & P&L'!E22+'Menu Costing'!W13*'Sales & P&L'!E23+'Menu Costing'!X13*'Sales & P&L'!E24)*(1+Assumptions!$B$48) -> 234.08 | F13: =D13/'Sides & Ingredients'!$E$50 -> 1.045 | G13: Mix fresh daily; cold rail. | H13: batches
A14: Banana pudding | B14: cup | C14: =('Menu Costing'!R14*'Sales & P&L'!D18)*(1+Assumptions!$B$48) -> 8.58 | D14: =('Menu Costing'!R14*'Sales & P&L'!C18)*(1+Assumptions!$B$48) -> 13.2 | E14: =('Menu Costing'!R14*'Sales & P&L'!E18)*(1+Assumptions!$B$48) -> 18.48 | F14: =D14/'Sides & Ingredients'!$E$61 -> 0.55 | G14: Day before; cups in reach-in. | H14: batches (24)
A15: Texas toast | B15: slice | C15: =('Menu Costing'!E15*'Sales & P&L'!D5+'Menu Costing'!F15*'Sales & P&L'!D6+'Menu Costing'!U15*'Sales & P&L'!D21+'Menu Costing'!V15*'Sales & P&L'!D22+'Menu Costing'!W15*'Sales & P&L'!D23+'Menu Costing'!X15*'Sales & P&L'!D24)*(1+Assumptions!$B$48) -> 91.52 | D15: =('Menu Costing'!E15*'Sales & P&L'!C5+'Menu Costing'!F15*'Sales & P&L'!C6+'Menu Costing'!U15*'Sales & P&L'!C21+'Menu Costing'!V15*'Sales & P&L'!C22+'Menu Costing'!W15*'Sales & P&L'!C23+'Menu Costing'!X15*'Sales & P&L'!C24)*(1+Assumptions!$B$48) -> 140.8 | E15: =('Menu Costing'!E15*'Sales & P&L'!E5+'Menu Costing'!F15*'Sales & P&L'!E6+'Menu Costing'!U15*'Sales & P&L'!E21+'Menu Costing'!V15*'Sales & P&L'!E22+'Menu Costing'!W15*'Sales & P&L'!E23+'Menu Costing'!X15*'Sales & P&L'!E24)*(1+Assumptions!$B$48) -> 197.12 | F15: =D15/20 -> 7.04 | G15: Toast to order on griddle. | H15: loaves (20 sl)
A16: Pickles | B16: oz | C16: =('Menu Costing'!E16*'Sales & P&L'!D5+'Menu Costing'!F16*'Sales & P&L'!D6+'Menu Costing'!U16*'Sales & P&L'!D21+'Menu Costing'!V16*'Sales & P&L'!D22+'Menu Costing'!W16*'Sales & P&L'!D23+'Menu Costing'!X16*'Sales & P&L'!D24)*(1+Assumptions!$B$48) -> 30.316 | D16: =('Menu Costing'!E16*'Sales & P&L'!C5+'Menu Costing'!F16*'Sales & P&L'!C6+'Menu Costing'!U16*'Sales & P&L'!C21+'Menu Costing'!V16*'Sales & P&L'!C22+'Menu Costing'!W16*'Sales & P&L'!C23+'Menu Costing'!X16*'Sales & P&L'!C24)*(1+Assumptions!$B$48) -> 46.64 | E16: =('Menu Costing'!E16*'Sales & P&L'!E5+'Menu Costing'!F16*'Sales & P&L'!E6+'Menu Costing'!U16*'Sales & P&L'!E21+'Menu Costing'!V16*'Sales & P&L'!E22+'Menu Costing'!W16*'Sales & P&L'!E23+'Menu Costing'!X16*'Sales & P&L'!E24)*(1+Assumptions!$B$48) -> 65.296 | F16: =D16 -> 46.64 | G16: Portion into 1 oz cups. | H16: oz
A17: Pickled onions | B17: oz | C17: =('Menu Costing'!E17*'Sales & P&L'!D5+'Menu Costing'!F17*'Sales & P&L'!D6+'Menu Costing'!G17*'Sales & P&L'!D7+'Menu Costing'!U17*'Sales & P&L'!D21+'Menu Costing'!V17*'Sales & P&L'!D22+'Menu Costing'!W17*'Sales & P&L'!D23+'Menu Costing'!X17*'Sales & P&L'!D24)*(1+Assumptions!$B$48) -> 34.749 | D17: =('Menu Costing'!E17*'Sales & P&L'!C5+'Menu Costing'!F17*'Sales & P&L'!C6+'Menu Costing'!G17*'Sales & P&L'!C7+'Menu Costing'!U17*'Sales & P&L'!C21+'Menu Costing'!V17*'Sales & P&L'!C22+'Menu Costing'!W17*'Sales & P&L'!C23+'Menu Costing'!X17*'Sales & P&L'!C24)*(1+Assumptions!$B$48) -> 53.46 | E17: =('Menu Costing'!E17*'Sales & P&L'!E5+'Menu Costing'!F17*'Sales & P&L'!E6+'Menu Costing'!G17*'Sales & P&L'!E7+'Menu Costing'!U17*'Sales & P&L'!E21+'Menu Costing'!V17*'Sales & P&L'!E22+'Menu Costing'!W17*'Sales & P&L'!E23+'Menu Costing'!X17*'Sales & P&L'!E24)*(1+Assumptions!$B$48) -> 74.844 | F17: =D17/'Sides & Ingredients'!$E$71 -> 0.66825 | G17: 2x per week. | H17: batches
A18: BBQ sauce | B18: oz | C18: =('Menu Costing'!E18*'Sales & P&L'!D5+'Menu Costing'!F18*'Sales & P&L'!D6+'Menu Costing'!I18*'Sales & P&L'!D9+'Menu Costing'!J18*'Sales & P&L'!D10+'Menu Costing'!K18*'Sales & P&L'!D11+'Menu Costing'!U18*'Sales & P&L'!D21+'Menu Costing'!V18*'Sales & P&L'!D22+'Menu Costing'!W18*'Sales & P&L'!D23+'Menu Costing'!X18*'Sales & P&L'!D24)*(1+Assumptions!$B$48) -> 119.262 | D18: =('Menu Costing'!E18*'Sales & P&L'!C5+'Menu Costing'!F18*'Sales & P&L'!C6+'Menu Costing'!I18*'Sales & P&L'!C9+'Menu Costing'!J18*'Sales & P&L'!C10+'Menu Costing'!K18*'Sales & P&L'!C11+'Menu Costing'!U18*'Sales & P&L'!C21+'Menu Costing'!V18*'Sales & P&L'!C22+'Menu Costing'!W18*'Sales & P&L'!C23+'Menu Costing'!X18*'Sales & P&L'!C24)*(1+Assumptions!$B$48) -> 183.48 | E18: =('Menu Costing'!E18*'Sales & P&L'!E5+'Menu Costing'!F18*'Sales & P&L'!E6+'Menu Costing'!I18*'Sales & P&L'!E9+'Menu Costing'!J18*'Sales & P&L'!E10+'Menu Costing'!K18*'Sales & P&L'!E11+'Menu Costing'!U18*'Sales & P&L'!E21+'Menu Costing'!V18*'Sales & P&L'!E22+'Menu Costing'!W18*'Sales & P&L'!E23+'Menu Costing'!X18*'Sales & P&L'!E24)*(1+Assumptions!$B$48) -> 256.872 | F18: =D18/128 -> 1.4334375 | G18: Portion 2 oz cups; 3 per sampler. | H18: gal
A19: Cuban bread | B19: each | C19: =('Menu Costing'!G19*'Sales & P&L'!D7+'Menu Costing'!H19*'Sales & P&L'!D8)*(1+Assumptions!$B$48) -> 33.605 | D19: =('Menu Costing'!G19*'Sales & P&L'!C7+'Menu Costing'!H19*'Sales & P&L'!C8)*(1+Assumptions!$B$48) -> 51.7 | E19: =('Menu Costing'!G19*'Sales & P&L'!E7+'Menu Costing'!H19*'Sales & P&L'!E8)*(1+Assumptions!$B$48) -> 72.38 | F19: =D19 -> 51.7 | G19: Bakery delivery daily 8:00. | H19: loaves
A20: Swiss | B20: oz | C20: =('Menu Costing'!G20*'Sales & P&L'!D7+'Menu Costing'!H20*'Sales & P&L'!D8)*(1+Assumptions!$B$48) -> 50.4075 | D20: =('Menu Costing'!G20*'Sales & P&L'!C7+'Menu Costing'!H20*'Sales & P&L'!C8)*(1+Assumptions!$B$48) -> 77.55 | E20: =('Menu Costing'!G20*'Sales & P&L'!E7+'Menu Costing'!H20*'Sales & P&L'!E8)*(1+Assumptions!$B$48) -> 108.57 | F20: =D20/16 -> 4.846875 | H20: lb
A21: Ham | B21: oz | C21: =('Menu Costing'!H21*'Sales & P&L'!D8)*(1+Assumptions!$B$48) -> 35.75 | D21: =('Menu Costing'!H21*'Sales & P&L'!C8)*(1+Assumptions!$B$48) -> 55 | E21: =('Menu Costing'!H21*'Sales & P&L'!E8)*(1+Assumptions!$B$48) -> 77 | F21: =D21/16 -> 3.4375 | H21: lb
A22: Salami | B22: oz | C22: =('Menu Costing'!H22*'Sales & P&L'!D8)*(1+Assumptions!$B$48) -> 17.875 | D22: =('Menu Costing'!H22*'Sales & P&L'!C8)*(1+Assumptions!$B$48) -> 27.5 | E22: =('Menu Costing'!H22*'Sales & P&L'!E8)*(1+Assumptions!$B$48) -> 38.5 | F22: =D22/16 -> 1.71875 | H22: lb
A23: Jerk aioli | B23: oz | C23: =('Menu Costing'!G23*'Sales & P&L'!D7+'Menu Costing'!H23*'Sales & P&L'!D8)*(1+Assumptions!$B$48) -> 21.27125 | D23: =('Menu Costing'!G23*'Sales & P&L'!C7+'Menu Costing'!H23*'Sales & P&L'!C8)*(1+Assumptions!$B$48) -> 32.725 | E23: =('Menu Costing'!G23*'Sales & P&L'!E7+'Menu Costing'!H23*'Sales & P&L'!E8)*(1+Assumptions!$B$48) -> 45.815 | F23: =D23/'Sides & Ingredients'!$E$81 -> 0.51132813 | H23: batches
A24: Guava BBQ | B24: oz | C24: =('Menu Costing'!H24*'Sales & P&L'!D8)*(1+Assumptions!$B$48) -> 8.9375 | D24: =('Menu Costing'!H24*'Sales & P&L'!C8)*(1+Assumptions!$B$48) -> 13.75 | E24: =('Menu Costing'!H24*'Sales & P&L'!E8)*(1+Assumptions!$B$48) -> 19.25 | F24: =D24/'Sides & Ingredients'!$E$90 -> 0.14322917 | H24: batches
A25: Butter | B25: oz | C25: =('Menu Costing'!G25*'Sales & P&L'!D7+'Menu Costing'!H25*'Sales & P&L'!D8)*(1+Assumptions!$B$48) -> 16.8025 | D25: =('Menu Costing'!G25*'Sales & P&L'!C7+'Menu Costing'!H25*'Sales & P&L'!C8)*(1+Assumptions!$B$48) -> 25.85 | E25: =('Menu Costing'!G25*'Sales & P&L'!E7+'Menu Costing'!H25*'Sales & P&L'!E8)*(1+Assumptions!$B$48) -> 36.19 | F25: =D25/16 -> 1.615625 | H25: lb
A26: Fountain drink | B26: each | C26: =('Menu Costing'!S26*'Sales & P&L'!D19)*(1+Assumptions!$B$48) -> 28.6 | D26: =('Menu Costing'!S26*'Sales & P&L'!C19)*(1+Assumptions!$B$48) -> 44 | E26: =('Menu Costing'!S26*'Sales & P&L'!E19)*(1+Assumptions!$B$48) -> 61.6 | F26: =D26 -> 44 | G26: Fountain: check syrup bags and CO2 at open. | H26: cups
A27: Cornbread | B27: piece | C27: =('Menu Costing'!T27*'Sales & P&L'!D20)*(1+Assumptions!$B$48) -> 8.58 | D27: =('Menu Costing'!T27*'Sales & P&L'!C20)*(1+Assumptions!$B$48) -> 13.2 | E27: =('Menu Costing'!T27*'Sales & P&L'!E20)*(1+Assumptions!$B$48) -> 18.48 | F27: =D27/'Sides & Ingredients'!$E$100 -> 0.33 | G27: Bake in combi 8:30; cut 40 per pan. Bake a second pan for catering days. | H27: sheet pans (40 pc)
A28: Tallow honey butter | B28: oz | C28: =('Menu Costing'!T28*'Sales & P&L'!D20)*(1+Assumptions!$B$48) -> 4.29 | D28: =('Menu Costing'!T28*'Sales & P&L'!C20)*(1+Assumptions!$B$48) -> 6.6 | E28: =('Menu Costing'!T28*'Sales & P&L'!E20)*(1+Assumptions!$B$48) -> 9.24 | F28: =D28/'Sides & Ingredients'!$E$110 -> 0.20625 | G28: Whip butter, rendered brisket tallow and honey; portion 0.5 oz cups. | H28: batches (32 oz)
A30: Daily timeline (lunch 11:00 - 2:30)
A31: 8:00 | B31: Bakery drop (Cuban bread). Check walk-in temps, log.
A32: 8:30 | B32: Combi: reheat brisket, pork, ribs, sausage. Kettle: mac.
A33: 9:30 | B33: Kettle: beans. Slaw mixed. Sauces and pickles portioned.
A34: 7:00 | B34: Opener loads the store smoker with seasoned chicken leg quarters (daily fresh smoke).
A35: 10:30 | B35: Chicken off the smoker into the Alto-Shaam. Load hot wells.
A36: 10:30 | B36: Pre-order bags staged on to-go shelf by pickup time. Line check, temps logged.
A37: 11:00 | B37: Open. Re-fire mac/beans at 12:00 on Base/Strong days.
A38: 2:30 | B38: Close the lunch line. Leftover meats chilled, vac-sealed, dated. Lunch crew cleans down and leaves by 3:30.
A39: 2:30-7:00 | B39: EVENING CATERING PICKUPS ONLY - one crew member. Party Samplers built from the hot hold, staged on the to-go shelf by pickup time. No walk-in service.
A40: 7:00 | B40: Last catering pickup. Close, count, send tomorrow's order to the commissary.

Sheet Order Guide
A1: Order guide - weekly meat order from the commissary
A2: Store orders meats only from the commissary. Weekly need = daily par x days open. Split into two deliveries.
A4: Meat | B4: Unit | C4: Weekly need (Base) | D4: Weekly delivery (Tuesday) | E4: Emergency run (as needed) | F4: Transfer price | G4: Weekly cost to store | H4: Commissary raw lb to buy | I4: Raw cases (approx)
A5: Brisket (sliced) | B5: cooked lb | C5: ='Prep List'!$D$5*Assumptions!$B$5 -> 100.1 | D5: =C5 -> 100.1 | E5: as needed | F5: ='Meat Cost & Transfer'!$J$5 -> 17.330246 | G5: =C5*F5 -> 1734.7576 | H5: =C5/Assumptions!$B$39 -> 200.2 | I5: =H5/60 -> 3.3366667 | J5: case ~60 lb (4 Prime packers)
A6: Pulled pork | B6: cooked lb | C6: ='Prep List'!$D$6*Assumptions!$B$5 -> 106.90625 | D6: =C6 -> 106.90625 | E6: as needed | F6: ='Meat Cost & Transfer'!$J$6 -> 7.4593145 | G6: =C6*F6 -> 797.44734 | H6: =C6/Assumptions!$B$40 -> 194.375 | I6: =H6/70 -> 2.7767857 | J6: case ~70 lb (8 butts)
A7: Burnt ends | B7: cooked lb | C7: ='Prep List'!$D$7*Assumptions!$B$5 -> 11 | D7: =C7 -> 11 | E7: as needed | F7: ='Meat Cost & Transfer'!$J$7 -> 11.296038 | G7: =C7*F7 -> 124.25642 | H7: =C7/Assumptions!$B$41 -> 18.333333 | I7: =H7/60 -> 0.30555556 | J7: case ~60 lb
A8: Spare ribs | B8: racks | C8: ='Prep List'!$D$8/Assumptions!$B$43*Assumptions!$B$5 -> 39.233333 | D8: =C8 -> 39.233333 | E8: as needed | F8: ='Meat Cost & Transfer'!$J$8 -> 17.94668 | G8: =C8*F8 -> 704.10809 | H8: =C8*Assumptions!$B$42 -> 137.31667 | I8: =H8/35 -> 3.9233333 | J8: case ~35 lb (10 racks)
A9: Chicken leg quarters | B9: each | C9: ='Prep List'!$D$9*Assumptions!$B$5 -> 176.55 | D9: =C9 -> 176.55 | E9: as needed | F9: ='Meat Cost & Transfer'!$J$9 -> 0.759375 | G9: =C9*F9 -> 134.06766 | H9: =C9*Assumptions!$B$44 -> 132.4125 | I9: =H9/40 -> 3.3103125 | J9: 40 lb case
A10: Jalapeno cheddar sausage | B10: links | C10: ='Prep List'!$D$10*Assumptions!$B$5 -> 202.4 | D10: =C10 -> 202.4 | E10: as needed | F10: ='Meat Cost & Transfer'!$J$10 -> 2.2194057 | G10: =C10*F10 -> 449.20772 | H10: =C10/Assumptions!$B$45 -> 50.6 | I10: =H10/10 -> 5.06 | J10: 10 lb case
A11: Weekly meat bill to store | G11: =SUM(G5:G10) -> 3943.8448 | H11: =SUM(H5:H10) -> 733.2375
A13: One delivery a week (Tuesday) covers the whole week, vac-packed and dated; emergency runs only when the store runs short. Chicken leg quarters ship RAW on the weekly delivery and are smoked fresh every day in the store smoker.

Sheet Shopping Guide
A1: Shopping guide - what the store buys each week (everything except meat)
A2: Batches per week = weekly use / batch yield, rounded up. Ingredient quantities = batches x recipe. Base scenario.
A4: Item | B4: Batches / wk | C4: Qty / wk | D4: Unit | E4: Est. cost / wk | F4: Buy as (pack) | G4: Supplier
A5: Beef tallow smoked mac & cheese
A6: Cavatappi | B6: =ROUNDUP('Prep List'!$D$11*Assumptions!$B$5/'Sides & Ingredients'!$E$25,0) -> 13 | C6: =B6*'Sides & Ingredients'!$B$17 -> 52 | D6: lb | E6: =C6*'Sides & Ingredients'!$D$17 -> 93.392 | F6: 4 x 5 lb | G6: Cheney Bros / US Foods
A7: Smoked cheddar | B7: =B6 -> 13 | C7: =B7*'Sides & Ingredients'!$B$18 -> 39 | D7: lb | E7: =C7*'Sides & Ingredients'!$D$18 -> 218.01 | F7: 4 x 2.25 lb | G7: Cheney Bros / US Foods
A8: Smoked gouda | B8: =B6 -> 13 | C8: =B8*'Sides & Ingredients'!$B$19 -> 39 | D8: lb | E8: =C8*'Sides & Ingredients'!$D$19 -> 205.53 | F8: 2 x 6 lb | G8: Cheney Bros / US Foods
A9: Whole milk | B9: =B6 -> 13 | C9: =B9*'Sides & Ingredients'!$B$20 -> 13 | D9: gal | E9: =C9*'Sides & Ingredients'!$D$20 -> 85.8325 | F9: 4 x 1 gal | G9: Cheney Bros / US Foods
A10: Heavy cream | B10: =B6 -> 13 | C10: =B10*'Sides & Ingredients'!$B$21 -> 26 | D10: qt | E10: =C10*'Sides & Ingredients'!$D$21 -> 120.4008 | F10: 12 x 1 qt | G10: Cheney Bros / US Foods
A11: Butter | B11: =B6 -> 13 | C11: =B11*'Sides & Ingredients'!$B$22 -> 13 | D11: lb | E11: =C11*'Sides & Ingredients'!$D$22 -> 30.3407 | F11: 36 x 1 lb | G11: Cheney Bros / US Foods
A12: Seasoning | B12: =B6 -> 13 | C12: =B12*'Sides & Ingredients'!$B$23 -> 13 | D12: batch | E12: =C12*'Sides & Ingredients'!$D$23 -> 19.5 | G12: Cheney Bros / US Foods
A13: Cowboy beans (brisket)
A14: Baked beans, #10 can | B14: =ROUNDUP('Prep List'!$D$12*Assumptions!$B$5/'Sides & Ingredients'!$E$38,0) -> 6 | C14: =B14*'Sides & Ingredients'!$B$30 -> 18 | D14: can | E14: =C14*'Sides & Ingredients'!$D$30 -> 138.3894 | F14: 6 x #10 case | G14: Cheney Bros / US Foods
A15: Brisket trim / burnt ends trim | B15: =B14 -> 6 | C15: =B15*'Sides & Ingredients'!$B$31 -> 12 | D15: lb | E15: =C15*'Sides & Ingredients'!$D$31 -> 24 | F15: commissary trim (internal value) | G15: In-house
A16: Yellow onion | B16: =B14 -> 6 | C16: =B16*'Sides & Ingredients'!$B$32 -> 6 | D16: lb | E16: =C16*'Sides & Ingredients'!$D$32 -> 5.4 | F16: 50 lb sack | G16: Cheney Bros / US Foods
A17: Bell pepper | B17: =B14 -> 6 | C17: =B17*'Sides & Ingredients'!$B$33 -> 3 | D17: lb | E17: =C17*'Sides & Ingredients'!$D$33 -> 4.5 | F17: case | G17: Cheney Bros / US Foods
A18: House BBQ sauce | B18: =B14 -> 6 | C18: =B18*'Sides & Ingredients'!$B$34 -> 192 | D18: oz | E18: =C18*'Sides & Ingredients'!$D$34 -> 21.19875 | G18: In-house
A19: Brown sugar | B19: =B14 -> 6 | C19: =B19*'Sides & Ingredients'!$B$35 -> 6 | D19: lb | E19: =C19*'Sides & Ingredients'!$D$35 -> 8.0232 | F19: 25 lb bag | G19: Cheney Bros / US Foods
A20: Mustard / spice | B20: =B14 -> 6 | C20: =B20*'Sides & Ingredients'!$B$36 -> 6 | D20: batch | E20: =C20*'Sides & Ingredients'!$D$36 -> 6 | G20: Cheney Bros / US Foods
A21: Apple coleslaw
A22: Coleslaw mix | B22: =ROUNDUP('Prep List'!$D$13*Assumptions!$B$5/'Sides & Ingredients'!$E$50,0) -> 6 | C22: =B22*'Sides & Ingredients'!$B$43 -> 30 | D22: lb | E22: =C22*'Sides & Ingredients'!$D$43 -> 45.465 | F22: 4 x 5 lb | G22: Cheney Bros / US Foods
A23: Apples | B23: =B22 -> 6 | C23: =B23*'Sides & Ingredients'!$B$44 -> 18 | D23: lb | E23: =C23*'Sides & Ingredients'!$D$44 -> 25.4448 | F23: 12 x 3 lb | G23: Cheney Bros / US Foods
A24: Mayonnaise | B24: =B22 -> 6 | C24: =B24*'Sides & Ingredients'!$B$45 -> 384 | D24: oz | E24: =C24*'Sides & Ingredients'!$D$45 -> 42.3936 | F24: 4 x 1 gal | G24: Cheney Bros / US Foods
A25: Vinegar | B25: =B22 -> 6 | C25: =B25*'Sides & Ingredients'!$B$46 -> 96 | D25: oz | E25: =C25*'Sides & Ingredients'!$D$46 -> 4.8 | F25: 4 x 1 gal | G25: Cheney Bros / US Foods
A26: Sugar | B26: =B22 -> 6 | C26: =B26*'Sides & Ingredients'!$B$47 -> 6 | D26: lb | E26: =C26*'Sides & Ingredients'!$D$47 -> 4.6992 | F26: 50 lb bag | G26: Cheney Bros / US Foods
A27: Seasoning | B27: =B22 -> 6 | C27: =B27*'Sides & Ingredients'!$B$48 -> 6 | D27: batch | E27: =C27*'Sides & Ingredients'!$D$48 -> 3 | G27: Cheney Bros / US Foods
A28: From-scratch banana pudding
A29: Vanilla pudding base | B29: =ROUNDUP('Prep List'!$D$14*Assumptions!$B$5/'Sides & Ingredients'!$E$61,0) -> 3 | C29: =B29*'Sides & Ingredients'!$B$55 -> 6 | D29: lb | E29: =C29*'Sides & Ingredients'!$D$55 -> 27 | F29: 6 x #10 or 12 x 2 lb | G29: Cheney Bros / US Foods
A30: Whole milk | B30: =B29 -> 3 | C30: =B30*'Sides & Ingredients'!$B$56 -> 3 | D30: gal | E30: =C30*'Sides & Ingredients'!$D$56 -> 19.8075 | F30: 4 x 1 gal | G30: Cheney Bros / US Foods
A31: Bananas | B31: =B29 -> 3 | C31: =B31*'Sides & Ingredients'!$B$57 -> 18 | D31: lb | E31: =C31*'Sides & Ingredients'!$D$57 -> 11.7 | F31: 40 lb case | G31: Cheney Bros / US Foods
A32: Vanilla wafers | B32: =B29 -> 3 | C32: =B32*'Sides & Ingredients'!$B$58 -> 6 | D32: lb | E32: =C32*'Sides & Ingredients'!$D$58 -> 32.34 | F32: 2 x 2 lb | G32: Cheney Bros / US Foods
A33: Whipped topping | B33: =B29 -> 3 | C33: =B33*'Sides & Ingredients'!$B$59 -> 6 | D33: lb | E33: =C33*'Sides & Ingredients'!$D$59 -> 21 | F33: case | G33: Cheney Bros / US Foods
A34: Pickled red onions
A35: Red onions | B35: =ROUNDUP('Prep List'!$D$17*Assumptions!$B$5/'Sides & Ingredients'!$E$71,0) -> 4 | C35: =B35*'Sides & Ingredients'!$B$66 -> 20 | D35: lb | E35: =C35*'Sides & Ingredients'!$D$66 -> 20.776 | F35: 25 lb | G35: Cheney Bros / US Foods
A36: Vinegar | B36: =B35 -> 4 | C36: =B36*'Sides & Ingredients'!$B$67 -> 128 | D36: oz | E36: =C36*'Sides & Ingredients'!$D$67 -> 5.1584 | F36: 4 x 1 gal | G36: Cheney Bros / US Foods
A37: Sugar | B37: =B35 -> 4 | C37: =B37*'Sides & Ingredients'!$B$68 -> 2 | D37: lb | E37: =C37*'Sides & Ingredients'!$D$68 -> 1.5664 | F37: 50 lb bag | G37: Cheney Bros / US Foods
A38: Salt / spice | B38: =B35 -> 4 | C38: =B38*'Sides & Ingredients'!$B$69 -> 4 | D38: batch | E38: =C38*'Sides & Ingredients'!$D$69 -> 1.2 | G38: Cheney Bros / US Foods
A39: House BBQ sauce (Sweet Eddie / Carolina Gold / Spicy avg)
A40: Ketchup, #10 can | B40: =ROUNDUP(('Prep List'!$D$18*Assumptions!$B$5+'Sides & Ingredients'!$B$34*$B$14+'Sides & Ingredients'!$B$87*$B$51)/'Sides & Ingredients'!$E$12,0) -> 10 | C40: =B40*'Sides & Ingredients'!$B$6 -> 10 | D40: can | E40: =C40*'Sides & Ingredients'!$D$6 -> 78.533 | F40: 6 x #10 case | G40: Cheney Bros / US Foods
A41: Brown sugar | B41: =B40 -> 10 | C41: =B41*'Sides & Ingredients'!$B$7 -> 20 | D41: lb | E41: =C41*'Sides & Ingredients'!$D$7 -> 26.744 | F41: 25 lb bag | G41: Cheney Bros / US Foods
A42: Vinegar | B42: =B40 -> 10 | C42: =B42*'Sides & Ingredients'!$B$8 -> 160 | D42: oz | E42: =C42*'Sides & Ingredients'!$D$8 -> 6.448 | F42: 4 x 1 gal | G42: Cheney Bros / US Foods
A43: Worcestershire | B43: =B40 -> 10 | C43: =B43*'Sides & Ingredients'!$B$9 -> 80 | D43: oz | E43: =C43*'Sides & Ingredients'!$D$9 -> 9.6 | F43: 4 x 1 gal | G43: Cheney Bros / US Foods
A44: Spices / rub | B44: =B40 -> 10 | C44: =B44*'Sides & Ingredients'!$B$10 -> 10 | D44: batch | E44: =C44*'Sides & Ingredients'!$D$10 -> 20 | F44: Flashover rub, in-house | G44: Cheney Bros / US Foods
A45: Jerk mayo-mustard-relish aioli (Smokin' Cuban)
A46: Mayonnaise | B46: =ROUNDUP('Prep List'!$D$23*Assumptions!$B$5/'Sides & Ingredients'!$E$81,0) -> 3 | C46: =B46*'Sides & Ingredients'!$B$76 -> 144 | D46: oz | E46: =C46*'Sides & Ingredients'!$D$76 -> 15.8976 | F46: 4 x 1 gal | G46: Cheney Bros / US Foods
A47: Yellow mustard | B47: =B46 -> 3 | C47: =B47*'Sides & Ingredients'!$B$77 -> 24 | D47: oz | E47: =C47*'Sides & Ingredients'!$D$77 -> 1.8816 | F47: 4 x 1 gal | G47: Cheney Bros / US Foods
A48: Sweet relish | B48: =B46 -> 3 | C48: =B48*'Sides & Ingredients'!$B$78 -> 24 | D48: oz | E48: =C48*'Sides & Ingredients'!$D$78 -> 2.4 | F48: 4 x 1 gal | G48: Cheney Bros / US Foods
A49: Jerk seasoning | B49: =B46 -> 3 | C49: =B49*'Sides & Ingredients'!$B$79 -> 3 | D49: batch | E49: =C49*'Sides & Ingredients'!$D$79 -> 3 | G49: Cheney Bros / US Foods
A50: Guava BBQ sauce
A51: Guava paste | B51: =ROUNDUP('Prep List'!$D$24*Assumptions!$B$5/'Sides & Ingredients'!$E$90,0) -> 1 | C51: =B51*'Sides & Ingredients'!$B$86 -> 2 | D51: lb | E51: =C51*'Sides & Ingredients'!$D$86 -> 7 | F51: case | G51: Cheney Bros / US Foods
A52: House BBQ sauce | B52: =B51 -> 1 | C52: =B52*'Sides & Ingredients'!$B$87 -> 64 | D52: oz | E52: =C52*'Sides & Ingredients'!$D$87 -> 7.06625 | G52: In-house
A53: Vinegar | B53: =B51 -> 1 | C53: =B53*'Sides & Ingredients'!$B$88 -> 8 | D53: oz | E53: =C53*'Sides & Ingredients'!$D$88 -> 0.3224 | F53: 4 x 1 gal | G53: Cheney Bros / US Foods
A54: Cornbread (sheet pan)
A55: Cornbread mix, 64 oz bag | B55: =ROUNDUP('Prep List'!$D$27*Assumptions!$B$5/'Sides & Ingredients'!$E$100,0) -> 2 | C55: =B55*'Sides & Ingredients'!$B$95 -> 2 | D55: bag | E55: =C55*'Sides & Ingredients'!$D$95 -> 29.46 | F55: 4 x 64 oz | G55: Cheney Bros / US Foods
A56: Eggs | B56: =B55 -> 2 | C56: =B56*'Sides & Ingredients'!$B$96 -> 12 | D56: each | E56: =C56*'Sides & Ingredients'!$D$96 -> 1.7796 | F56: 15 dozen | G56: Cheney Bros / US Foods
A57: Whole milk | B57: =B55 -> 2 | C57: =B57*'Sides & Ingredients'!$B$97 -> 1 | D57: gal | E57: =C57*'Sides & Ingredients'!$D$97 -> 6.6025 | F57: 4 x 1 gal | G57: Cheney Bros / US Foods
A58: Butter (melted, in batter) | B58: =B55 -> 2 | C58: =B58*'Sides & Ingredients'!$B$98 -> 1 | D58: lb | E58: =C58*'Sides & Ingredients'!$D$98 -> 2.3339 | F58: 36 x 1 lb | G58: Cheney Bros / US Foods
A59: Tallow honey butter
A60: Butter | B60: =ROUNDUP('Prep List'!$D$28*Assumptions!$B$5/'Sides & Ingredients'!$E$110,0) -> 2 | C60: =B60*'Sides & Ingredients'!$B$105 -> 2.5 | D60: lb | E60: =C60*'Sides & Ingredients'!$D$105 -> 5.83475 | F60: 36 x 1 lb | G60: Cheney Bros / US Foods
A61: Beef tallow (rendered brisket trim) | B61: =B60 -> 2 | C61: =B61*'Sides & Ingredients'!$B$106 -> 1 | D61: lb | E61: =C61*'Sides & Ingredients'!$D$106 -> 1 | F61: commissary trim (internal value) | G61: In-house
A62: Honey | B62: =B60 -> 2 | C62: =B62*'Sides & Ingredients'!$B$107 -> 8 | D62: oz | E62: =C62*'Sides & Ingredients'!$D$107 -> 1.1696 | F62: 6 x 5 lb | G62: Cheney Bros / US Foods
A63: Salt | B63: =B60 -> 2 | C63: =B63*'Sides & Ingredients'!$B$108 -> 2 | D63: batch | E63: =C63*'Sides & Ingredients'!$D$108 -> 0.1 | G63: Cheney Bros / US Foods
A64: Bread, deli, pickles, drinks
A65: Texas toast | C65: =ROUNDUP('Prep List'!$D$15*Assumptions!$B$5/20,0) -> 36 | D65: loaves | E65: =C65*20*'Sides & Ingredients'!$D$115 -> 201.096 | F65: 20-slice Texas toast | G65: Bakery / Cheney
A66: Cuban bread | C66: =ROUNDUP('Prep List'!$D$19*Assumptions!$B$5,0) -> 259 | D66: loaves | E66: =C66*'Sides & Ingredients'!$D$117 -> 121.73 | F66: Cuban bread, daily | G66: Tampa Cuban bakery
A67: Swiss | C67: =ROUNDUP('Prep List'!$D$20*Assumptions!$B$5/16,0) -> 25 | D67: lb | E67: =C67*16*'Sides & Ingredients'!$D$118 -> 113.24 | F67: 4 x 5 lb sliced | G67: Cheney Bros / US Foods
A68: Ham | C68: =ROUNDUP('Prep List'!$D$21*Assumptions!$B$5/16,0) -> 18 | D68: lb | E68: =C68*16*'Sides & Ingredients'!$D$119 -> 80.8128 | F68: 2 x 6 lb | G68: Cheney Bros / US Foods
A69: Salami | C69: =ROUNDUP('Prep List'!$D$22*Assumptions!$B$5/16,0) -> 9 | D69: lb | E69: =C69*16*'Sides & Ingredients'!$D$120 -> 54 | F69: 2 x 6 lb | G69: Cheney Bros / US Foods
A70: Butter | C70: =ROUNDUP('Prep List'!$D$25*Assumptions!$B$5/16,0) -> 9 | D70: lb | E70: =C70*16*'Sides & Ingredients'!$D$121 -> 21.0096 | F70: 36 x 1 lb | G70: Cheney Bros / US Foods
A71: Pickles | C71: =ROUNDUP('Prep List'!$D$16*Assumptions!$B$5/80,0) -> 3 | D71: gal jars | E71: =C71*80*'Sides & Ingredients'!$D$116 -> 32.808 | F71: 4 x 1 gal | G71: Cheney Bros / US Foods
A72: Fountain drink | C72: =ROUNDUP('Prep List'!$D$26*Assumptions!$B$5,0) -> 220 | D72: cups | E72: =C72*'Sides & Ingredients'!$D$128 -> 115.324 | F72: Syrup bag-in-box + 24 oz cups/lids/straws | G72: Pepsi fountain program
A73: Packaging (units per week)
A74: Sampler 2-3 kits | C74: =ROUNDUP(('Sales & P&L'!$C$5)*Assumptions!$B$5*(1+Assumptions!$B$48),0) -> 77 | D74: each | E74: =C74*'Sides & Ingredients'!$D$122 -> 179.102 | G74: Restaurant Depot / WebstaurantStore
A75: Sampler 5-6 kits | C75: =ROUNDUP(('Sales & P&L'!$C$6)*Assumptions!$B$5*(1+Assumptions!$B$48),0) -> 17 | D75: each | E75: =C75*'Sides & Ingredients'!$D$123 -> 65.586 | G75: Restaurant Depot / WebstaurantStore
A76: Cuban wraps + baskets | C76: =ROUNDUP(('Sales & P&L'!$C$7+'Sales & P&L'!$C$8)*Assumptions!$B$5*(1+Assumptions!$B$48),0) -> 259 | D76: each | E76: =C76*'Sides & Ingredients'!$D$124 -> 78.218 | G76: Restaurant Depot / WebstaurantStore
A77: 6 oz cups + lids | C77: =ROUNDUP(('Sales & P&L'!$C$15+'Sales & P&L'!$C$16+'Sales & P&L'!$C$17)*Assumptions!$B$5*(1+Assumptions!$B$48),0) -> 110 | D77: each | E77: =C77*'Sides & Ingredients'!$D$125 -> 27.83 | G77: Restaurant Depot / WebstaurantStore
A78: Pudding cups | C78: =ROUNDUP(('Sales & P&L'!$C$18)*Assumptions!$B$5*(1+Assumptions!$B$48),0) -> 66 | D78: each | E78: =C78*'Sides & Ingredients'!$D$126 -> 19.998 | G78: Restaurant Depot / WebstaurantStore
A79: Pre-order pans + bags | C79: =ROUNDUP(('Sales & P&L'!$C$9+'Sales & P&L'!$C$10+'Sales & P&L'!$C$11+'Sales & P&L'!$C$12)*Assumptions!$B$5*(1+Assumptions!$B$48),0) -> 66 | D79: each | E79: =C79*'Sides & Ingredients'!$D$127 -> 128.304 | G79: Restaurant Depot / WebstaurantStore
A80: Party Sampler 10 kits | C80: =ROUNDUP(('Sales & P&L'!$C$21)*Assumptions!$B$5*(1+Assumptions!$B$48),0) -> 5 | D80: each | E80: =C80*'Sides & Ingredients'!$D$129 -> 55.08 | G80: Restaurant Depot / WebstaurantStore
A81: Party Sampler 20 kits | C81: =ROUNDUP(('Sales & P&L'!$C$22)*Assumptions!$B$5*(1+Assumptions!$B$48),0) -> 3 | D81: each | E81: =C81*'Sides & Ingredients'!$D$130 -> 59.214 | G81: Restaurant Depot / WebstaurantStore
A82: Party Sampler 30 kits | C82: =ROUNDUP(('Sales & P&L'!$C$23)*Assumptions!$B$5*(1+Assumptions!$B$48),0) -> 2 | D82: each | E82: =C82*'Sides & Ingredients'!$D$131 -> 51.994 | G82: Restaurant Depot / WebstaurantStore
A83: Party Sampler 50 kits | C83: =ROUNDUP(('Sales & P&L'!$C$24)*Assumptions!$B$5*(1+Assumptions!$B$48),0) -> 1 | D83: each | E83: =C83*'Sides & Ingredients'!$D$132 -> 42.347 | G83: Restaurant Depot / WebstaurantStore
A85: Weekly store purchases (non-meat), Base | E85: =SUM(E5:E83) -> 2921.7348
A86: Order rhythm: broadline order Thursday for Friday delivery (matches the commissary cadence); bakery daily; Restaurant Depot run Monday for packaging and drinks.

Sheet Smoke Schedule
A1: Commissary smoke schedule for the store
A2: Store open Tue-Sat lunch. Commissary smokes Sun-Tue (Anthony's cadence), chills and vac-packs, delivers twice a week. Chicken is the only thing smoked fresh.
A4: Day | B4: Commissary | C4: Store | D4: Brisket packers to smoke | E4: Pork butts to smoke | F4: Notes
A5: Thursday | B5: Broadline + meat orders placed (Cheney / US Foods / direct purveyor). | C5: Open. Send next week's forecast to commissary by 4 pm. | F5: Raw meat delivered Friday.
A6: Friday | B6: Raw meat delivery; trim and rub briskets and butts. | C6: Open.
A7: Saturday | B7: Catering as booked. | C7: Open.
A8: Sunday | B8: SMOKE: all briskets for the week (overnight). | C8: Closed. | D8: =ROUNDUP('Order Guide'!$H$5/Assumptions!$B$46,0) -> 15 | F8: Brisket rests, sliced-ready, chilled < 41F within 6 hrs, vac-packed.
A9: Monday | B9: SMOKE: pork butts + pork belly. Chill + vac-pack brisket. Pack raw chicken for the store. | C9: Closed. Prep sides for Tuesday. | E9: =ROUNDUP('Order Guide'!$H$6/Assumptions!$B$47,0) -> 22
A10: Tuesday | B10: SMOKE: ribs. 8:00 WEEKLY DELIVERY to the store (all meats for Tue-Sat). | C10: Open. Receive weekly delivery before 9:00, check temps, date and stock walk-in. | F10: Order Guide col D. Emergency run only if the store runs short.
A11: Wednesday | B11: Catering midweek. | C11: Open.
A13: Smoking: 2 smokers x 2 smokes a day on Sun/Mon/Tue at ~$15 of wood per smoke (Anthony). Commissary labor for this store ~20 hrs/week. Both feed the Commissary P&L.
A14: Chicken leg quarters: shipped raw on the weekly delivery and smoked fresh every service day in the store's Cookshack FEC120 (load 7:30, ready ~10:30). The store smoker can also run ribs or extra chicken on catering days.
A15: Emergency smokes only outside Sun-Tue (Anthony's rule). Prep extra into the next week: vac-packed, chilled brisket and pork hold safely for the week when kept at 41F or below and dated.
A16: Brisket packers and pork butts above cover the store's lunch, pre-orders and evening catering pickups (Base scenario). Catering delivered from the warehouse is on top of this.

Sheet Direct vs Distributor
A1: Meat buying: what you pay today vs buying direct
A2: Your current prices come from the Station House order guide (Centerpoint, Cheney). USDA wholesale is what packers sell at by the truckload - nobody your size buys at that price, but it shows how much room there is.
A4: Protein | B4: Supplier today | C4: You pay $/lb | D4: USDA wholesale $/lb | E4: Your price vs USDA | F4: Direct price $/lb (base case) | G4: Raw lb / week (store) | H4: Annual cost today | I4: Annual savings direct | J4: Savings %
A5: Brisket (Prime packer) | B5: US Foods | C5: =Assumptions!$B$31 -> 5.72 | D5: =Assumptions!$B$25 -> 4.92 | E5: =C5/D5-1 -> 0.16260163 | F5: =C5*(1-Assumptions!$B$37) -> 4.862 | G5: ='Order Guide'!$H$5 -> 200.2 | H5: =C5*G5*52 -> 59547.488 | I5: =(C5-F5)*G5*52 -> 8932.1232 | J5: =IF(H5=0,0,I5/H5) -> 0.15
A6: Pork butt | B6: Centerpoint | C6: =Assumptions!$B$32 -> 2.07 | D6: =Assumptions!$B$26 -> 1.23 | E6: =C6/D6-1 -> 0.68292683 | F6: =C6*(1-Assumptions!$B$37) -> 1.7595 | G6: ='Order Guide'!$H$6 -> 194.375 | H6: =C6*G6*52 -> 20922.525 | I6: =(C6-F6)*G6*52 -> 3138.3787 | J6: =IF(H6=0,0,I6/H6) -> 0.15
A7: Pork belly | B7: US Foods | C7: =Assumptions!$B$34 -> 4.21 | D7: =Assumptions!$B$28 -> 2.38 | E7: =C7/D7-1 -> 0.76890756 | F7: =C7*(1-Assumptions!$B$37) -> 3.5785 | G7: ='Order Guide'!$H$7 -> 18.333333 | H7: =C7*G7*52 -> 4013.5333 | I7: =(C7-F7)*G7*52 -> 602.03 | J7: =IF(H7=0,0,I7/H7) -> 0.15
A8: Spare ribs | B8: Cheney | C8: =Assumptions!$B$33 -> 2.89 | D8: =Assumptions!$B$27 -> 1.69 | E8: =C8/D8-1 -> 0.71005917 | F8: =C8*(1-Assumptions!$B$37) -> 2.4565 | G8: ='Order Guide'!$H$8 -> 137.31667 | H8: =C8*G8*52 -> 20635.949 | I8: =(C8-F8)*G8*52 -> 3095.3923 | J8: =IF(H8=0,0,I8/H8) -> 0.15
A9: Chicken leg quarters | B9: Centerpoint | C9: =Assumptions!$B$35 -> 0.81 | D9: =Assumptions!$B$29 -> 0.529 | E9: =C9/D9-1 -> 0.53119093 | F9: =C9*(1-Assumptions!$B$37) -> 0.6885 | G9: ='Order Guide'!$H$9 -> 132.4125 | H9: =C9*G9*52 -> 5577.2145 | I9: =(C9-F9)*G9*52 -> 836.58218 | J9: =IF(H9=0,0,I9/H9) -> 0.15
A10: Jalapeno cheddar sausage | B10: Centerpoint | C10: =Assumptions!$B$36 -> 5.89 | D10: n/a | E10: n/a | F10: =C10*(1-Assumptions!$B$37) -> 5.0065 | G10: ='Order Guide'!$H$10 -> 50.6 | H10: =C10*G10*52 -> 15497.768 | I10: =(C10-F10)*G10*52 -> 2324.6652 | J10: =IF(H10=0,0,I10/H10) -> 0.15
A11: Total (store only) | G11: =SUM(G5:G10) -> 733.2375 | H11: =SUM(H5:H10) -> 126194.48 | I11: =SUM(I5:I10) -> 18929.172 | J11: =IF(H11=0,0,I11/H11) -> 0.15
A13: Scale it to the whole business (store + catering)
A14: Whole-business meat volume as a multiple of the store | G14: 3 | H14: Input: if catering buys 2x what the store does, enter 3.
A15: Annual savings, whole business (base case) | I15: =I11*G14 -> 56787.515
A17: Sensitivity: annual savings at different direct-buying discounts
A18: Discount vs today | B18: Store only | C18: Whole business
A19: 0.1 | B19: =H11*A19 -> 12619.448 | C19: =B19*$G$14 -> 37858.343
A20: 0.15 | B20: =H11*A20 -> 18929.172 | C20: =B20*$G$14 -> 56787.515
A21: 0.2 | B21: =H11*A21 -> 25238.895 | C21: =B21*$G$14 -> 75716.686
A22: 0.3 | B22: =H11*A22 -> 37858.343 | C22: =B22*$G$14 -> 113575.03
A24: Brisket: US Foods Prime at $5.72/lb is about 16% over the USDA Prime packer benchmark ($4.92) - a fair price for Prime. Switching from Centerpoint ($7.82, Choice/Prime per the old order guide) to US Foods already saves roughly $2/lb. Pork belly is the biggest remaining gap until the US Foods price is entered.
A25: Centerpoint is already a meat purveyor, not a broadline distributor. Going "more direct" means a packer program (e.g. buying brisket by the combo or pallet through a packer rep or buying group), cash-and-carry on spot deals, or bidding Centerpoint against a second purveyor.
A26: Trade-offs of going direct: case/pallet minimums, fixed delivery days, shorter payment terms, and the commissary walk-in must hold the volume. Restaurant Depot has no minimums but you haul it yourself.
A27: Leverage: in a June 2026 operator survey, 70% got a price cut or credit just by showing a competing quote. Get one written quote and take it to Centerpoint and Cheney.
A28: The commissary keeps these savings: the store is charged cost + 25%, so cheaper raw meat lowers both the commissary's cost and the store's plate cost.

Sheet Commissary P&L
A1: Commissary P&L - what the commissary really clears from one store
A2: Base week. Raw meat at your supplier prices, plus the commissary's own labor, wood, bags and delivery. The process cost per raw pound feeds the transfer price, so the store is charged full cost + 25%.
B4: Per week | C4: Per month | E4: How it is calculated
A5: Volume
A6: Raw meat processed for this store (lb) | B6: ='Order Guide'!$H$11 -> 733.2375 | E6: Order Guide, Base scenario incl. prep buffer and evening catering
A8: Revenue
A9: Meat sold to the store (transfer price) | B9: ='Order Guide'!$G$11 -> 3943.8448 | C9: =B9*Assumptions!$B$6 -> 17076.848
A11: Costs
A12: Raw meat (US Foods Prime brisket, Centerpoint, Cheney) | B12: ='Order Guide'!$H$5*'Meat Cost & Transfer'!$D$5+'Order Guide'!$H$6*'Meat Cost & Transfer'!$D$6+'Order Guide'!$H$7*'Meat Cost & Transfer'!$D$7+'Order Guide'!$H$8*'Meat Cost & Transfer'!$D$8+'Order Guide'!$H$9*'Meat Cost & Transfer'!$D$9+'Order Guide'!$H$10*'Meat Cost & Transfer'!$D$10 -> 2426.8169 | C12: =B12*Assumptions!$B$6 -> 10508.117 | E12: Raw lb x what you pay per lb (includes raw chicken sold to the store)
A13: Commissary labor | B13: =Assumptions!$B$13*Assumptions!$B$14*(1+Assumptions!$B$73) -> 399.6 | C13: =B13*Assumptions!$B$6 -> 1730.268 | E13: 20 hrs/wk x rate + payroll taxes
A14: Wood | B14: =Assumptions!$B$15*Assumptions!$B$16*Assumptions!$B$17 -> 180 | C14: =B14*Assumptions!$B$6 -> 779.4 | E14: $15 a smoke x 4 smokes a day x 3 smoke days
A15: Vac bags, foil, labels | B15: =B6*Assumptions!$B$18 -> 58.659 | C15: =B15*Assumptions!$B$6 -> 253.99347
A16: Delivery (weekly + emergency runs) | B16: =Assumptions!$B$19*Assumptions!$B$20 -> 90 | C16: =B16*Assumptions!$B$6 -> 389.7
A17: Share of warehouse rent | B17: =Assumptions!$B$21*Assumptions!$B$22/Assumptions!$B$6 -> 0 | C17: =B17*Assumptions!$B$6 -> 0 | E17: 0% by default - see Assumptions
A18: Process cost (labor + wood + bags + delivery + rent share) | B18: =SUM(B13:B17) -> 728.259 | C18: =B18*Assumptions!$B$6 -> 3153.3615
A19: Raw lb the commissary smokes (all meat except chicken) | B19: =B6-'Order Guide'!$H$9 -> 600.825
A20: Process cost per raw lb smoked | B20: =IF(B19=0,0,B18/B19) -> 1.2120984 | E20: Feeds Assumptions -> transfer price. Chicken ships raw and is smoked at the store.
A21: Total commissary cost | B21: =B12+B18 -> 3155.0759 | C21: =B21*Assumptions!$B$6 -> 13661.479
A23: Profit
A24: Commissary profit from this store | B24: =B9-B21 -> 788.76897 | C24: =B24*Assumptions!$B$6 -> 3415.3696 | E24: Should equal the 25% markup on full cost
A25: Commissary margin on sales | B25: =IF(B9=0,0,B24/B9) -> 0.2
A26: Commissary profit per labor hour | B26: =B24/Assumptions!$B$13 -> 39.438448 | E26: What each commissary hour spent on this store earns
A28: The commissary runs at cost + 25% on FULL cost (raw meat + labor + wood + bags + delivery), so its profit is real, not just a paper markup.
A29: With rent share at 0%, this is the extra profit from running store volume through a warehouse you already pay for. Set a rent share on Assumptions to see a fully loaded number.
A30: Monthly figures here use the Order Guide (with the 10% prep buffer), so they run slightly above the commissary line on Sales & P&L.

Sheet Who Makes Money
A1: Who makes money - investor, Station House and the commissary
A2: One investor funds one store. Station House runs it, supplies the meat through the commissary at cost + 25%, takes a management fee and owns a share. All per year.
A4: Per year | B4: Conservative | C4: Base | D4: Strong | E4: How it is calculated
A5: The store
A6: Store sales (lunch + pre-orders + evening catering) | B6: ='Sales & P&L'!G36*12 -> 607847.56 | C6: ='Sales & P&L'!H36*12 -> 935150.1 | D6: ='Sales & P&L'!I36*12 -> 1309210.1
A7: Store profit before fees (EBITDA) | B7: ='Sales & P&L'!G68*12 -> 21145.872 | C7: ='Sales & P&L'!H68*12 -> 219584.67 | D7: ='Sales & P&L'!I68*12 -> 446371.86 | E7: Sales & P&L
A8: Station House management / brand fee | B8: =B6*Assumptions!$B$81 -> 18235.427 | C8: =C6*Assumptions!$B$81 -> 28054.503 | D8: =D6*Assumptions!$B$81 -> 39276.304 | E8: Sales x fee % (Assumptions)
A9: Store profit to split | B9: =B7-B8 -> 2910.4449 | C9: =C7-C8 -> 191530.16 | D9: =D7-D8 -> 407095.56
A11: Investor
A12: Cash the investor puts in | B12: ='Startup Budget'!$F$50*Assumptions!$B$80 -> 466213.91 | C12: ='Startup Budget'!$F$50*Assumptions!$B$80 -> 466213.91 | D12: ='Startup Budget'!$F$50*Assumptions!$B$80 -> 466213.91 | E12: Startup cost used in the plan x investor share funded
A13: Investor share of store profit | B13: =B9*(1-Assumptions!$B$79) -> 2037.3115 | C13: =C9*(1-Assumptions!$B$79) -> 134071.12 | D13: =D9*(1-Assumptions!$B$79) -> 284966.89 | E13: Profit x (1 - Station House ownership)
A14: Investor cash-on-cash return | B14: =IF(B12=0,0,B13/B12) -> 0.004369907 | C14: =IF(C12=0,0,C13/C12) -> 0.28757425 | D14: =IF(D12=0,0,D13/D12) -> 0.61123635
A15: Investor payback (years) | B15: =IF(B13<=0,"Not at this volume",B12/B13) -> 228.83782 | C15: =IF(C13<=0,"Not at this volume",C12/C13) -> 3.4773628 | D15: =IF(D13<=0,"Not at this volume",D12/D13) -> 1.6360284
A17: Station House (Anthony)
A18: Management / brand fee | B18: =B8 -> 18235.427 | C18: =C8 -> 28054.503 | D18: =D8 -> 39276.304
A19: Ownership share of store profit | B19: =B9*Assumptions!$B$79 -> 873.13348 | C19: =C9*Assumptions!$B$79 -> 57459.049 | D19: =D9*Assumptions!$B$79 -> 122128.67 | E19: Profit x Station House ownership %
A20: Commissary profit: 25% markup on every pound of meat the store buys | B20: ='Sales & P&L'!G72*12 -> 24218.076 | C20: ='Sales & P&L'!H72*12 -> 37258.578 | D20: ='Sales & P&L'!I72*12 -> 52162.009 | E20: Includes meat in evening catering Party Samplers
A21: Total to Station House from one store | B21: =B18+B19+B20 -> 43326.636 | C21: =C18+C19+C20 -> 122772.13 | D21: =D18+D19+D20 -> 213566.98
A22: Station House cash in | B22: ='Startup Budget'!$F$50*(1-Assumptions!$B$80) -> 0 | C22: ='Startup Budget'!$F$50*(1-Assumptions!$B$80) -> 0 | D22: ='Startup Budget'!$F$50*(1-Assumptions!$B$80) -> 0 | E22: Zero when the investor funds 100%
A24: Split of the money the store generates
A25: Store profit + commissary markup | B25: =B7+B20 -> 45363.947 | C25: =C7+C20 -> 256843.25 | D25: =D7+D20 -> 498533.87
A26: Investor share | B26: =IF(B25=0,0,B13/B25) -> 0.044910365 | C26: =IF(C25=0,0,C13/C25) -> 0.52199588 | D26: =IF(D25=0,0,D13/D25) -> 0.57160989
A27: Station House share | B27: =IF(B25=0,0,B21/B25) -> 0.95508963 | C27: =IF(C25=0,0,C21/C25) -> 0.47800412 | D27: =IF(D25=0,0,D21/D25) -> 0.42839011
A29: Scaling: each additional store run the same way adds to Station House
A30: 2 stores | B30: =B21*2 -> 86653.272 | C30: =C21*2 -> 245544.26 | D30: =D21*2 -> 427133.96
A31: 3 stores | B31: =B21*3 -> 129979.91 | C31: =C21*3 -> 368316.39 | D31: =D21*3 -> 640700.94
A32: 5 stores | B32: =B21*5 -> 216633.18 | C32: =C21*5 -> 613860.65 | D32: =D21*5 -> 1067834.9
A34: Ownership %, management fee % and how much the investor funds are inputs on Assumptions (yellow) - the deal is not set. Common operating-partner structures: 20-50% sweat equity for the operator, a 3-6% management or license fee, and the investor recouping capital first.
A35: Evening catering pickups (until 7 pm) are counted inside the store. The commissary earns its 25% on that meat too, and catering delivered from the warehouse stays 100% Station House.
A36: Not tax or legal advice - have your CPA and attorney structure the operating agreement.

Sheet Sources
A1: Sources
A3: What | B3: Source
A4: Seminole Heights sales mix, avg ticket, daily sales | B4: Square orders API, location L413E6TD6D669, completed orders Sep 18 - Oct 27, 2026 (1,000 orders)
A5: Ingredient, meat, drink and packaging prices | B5: Station House Order Guide (Centerpoint, Cheney, US Foods, La Segunda case prices)
A6: Menu prices | B6: Square catalog (Walk-In Samplers, Brisket Cuban, Smokin' Cuban) and Station House Commerce catalog
A7: USDA brisket Choice (IMPS 120) | B7: https://www.ams.usda.gov/mnreports/ams_2453.pdf (LM_XB403, Oct 26 2026)
A8: USDA Prime brisket | B8: https://www.ams.usda.gov/mnreports/ams_2460.pdf (LM_XB456, Oct 19 2026)
A9: USDA pork cutout (butt, spare ribs, belly) | B9: https://www.indexbox.io/blog/usda-morning-report-shows-mixed-pork-cutout-values/ (USDA morning report Oct 13 2026)
A10: USDA chicken leg quarters | B10: https://www.ams.usda.gov/mnreports/ams_3646.pdf (Oct 23 2026)
A11: Brisket price spike, Sept 2026 | B11: https://www.ky3.com/2026/09/29/brisket-prices-more-than-double-week-squeezing-bbq-restaurants-home-cooks/
A12: Sysco FY2026 gross margin 18.5% | B12: https://www.sec.gov/Archives/edgar/data/0000096021/000009602126000026/syy2026q4pressrelease.htm
A13: Restaurant Depot ~20% below broadline; 70% got price cuts with competing quotes | B13: https://assets.nationbuilder.com/irc/pages/5026/attachments/original/1783663394/IRC_Sysco_Survey_June_2026.pdf
A14: Rational iCombi Pro 6-full electric | B14: https://www.webstaurantstore.com/rational-icombi-pro-6-pan-full-size-electric-combi-oven-208-240v-3-phase/645ICP62I.html
... A29: Prep table pricing | B29: https://therestaurantwarehouse.com/blogs/restaurant-equipment/how-much-to-open-restaurant
